{"airport":[{"bdrp":"AVALON","iata":"AVV","port":"1","city":"AVALON, Australia"},{"bdrp":"AALBORG","iata":"AAL","port":"1","city":"Aalborg, Denmark"},{"bdrp":"AARHUS","iata":"AAR","port":"1","city":"Aarhus, Denmark"},{"bdrp":"MARSH HARBOUR","iata":"MHH","port":"1","city":"Abaco Island, Bahamas"},{"bdrp":"ABILENE","iata":"ABI","port":"1","city":"Abilene, United States"},{"bdrp":"ABU DHABI","iata":"AUH","port":"1","city":"Abu Dhabi, United Arab Emirates"},{"bdrp":"NNAMDI AZIKIWE","iata":"ABV","port":"1","city":"Abuja, Nigeria"},{"bdrp":"POINTE A PITRE","iata":"PTP","port":"1","city":"Abymes, France"},{"bdrp":"KOTOKA","iata":"ACC","port":"1","city":"Accra, Ghana"},{"bdrp":"TAKENGON REMBELE","iata":"TXE","city":"Aceh, Indonesia","port":"0"},{"bdrp":"ADANA SAKIRPASA","iata":"ADA","port":"1","city":"Adana, Turkey"},{"bdrp":"ADELAIDE","iata":"ADL","port":"1","city":"Adelaide, Australia"},{"bdrp":"OUED IRARA u2013KRIM BELKACEM","iata":"HME","port":"1","city":"Ageria, Algeria"},{"bdrp":"AGUASCALIENTES","iata":"AGU","port":"1","city":"Aguascalientes, Mexico"},{"bdrp":"SARDAR VALLABHBHAI PATEL","iata":"AMD","port":"1","city":"Ahmedabad, India"},{"bdrp":"ROMAN TMETUCHI","iata":"ROR","port":"1","city":"Airai, Babelthuap Island, Palau, Palau"},{"bdrp":"AKITA","iata":"AXT","port":"1","city":"Akita, Japan"},{"bdrp":"AKSU","iata":"AKU","port":"1","city":"Aksu, China"},{"bdrp":"AL AIN","iata":"AAN","port":"1","city":"Al Ain, United Arab Emirates"},{"bdrp":"JUAN SANTAMARIA","iata":"SJO","port":"1","city":"Alajuela Province, Costa Rica"},{"bdrp":"TED STEVENS ANCHORAGE","iata":"ANC","port":"1","city":"Alaska, United States"},{"bdrp":"ALBUQUERQUE","iata":"ABQ","port":"1","city":"Albuquerque, Mexico"},{"bdrp":"MCGHEE TYSON","iata":"TYS","port":"1","city":"Alcoa, Tennessee, United States"},{"bdrp":"ALICE SPRINGS","iata":"ASP","port":"1","city":"Alice Springs, Australia"},{"bdrp":"ALMATY","iata":"ALA","port":"1","city":"Almaty, Kazakhstan"},{"bdrp":"ALMERIA","iata":"LEI","port":"1","city":"Almeria, Spain"},{"bdrp":"MALI","iata":"ARD","city":"Alor Island, Indonesia","port":"0"},{"bdrp":"SULTAN ABDUL HALIM","iata":"AOR","port":"1","city":"Alor Setar, Malaysia"},{"bdrp":"GURNEY","iata":"GUR","port":"1","city":"Alotau, Papua New Guinea"},{"bdrp":"ALTAY","iata":"AAT","port":"1","city":"Altay, China"},{"bdrp":"RICK HUSBAND AMARILLO","iata":"AMA","port":"1","city":"Amarillo, United States"},{"bdrp":"PATTIMURA","iata":"AMQ","city":"Ambon, Indonesia","port":"0"},{"bdrp":"TANJUNG API","iata":"VPM","city":"Ampana, Indonesia","port":"0"},{"bdrp":"SCHIPHOL","iata":"AMS","port":"1","city":"Amsterdam, Netherlands"},{"bdrp":"MANANARA NORD","iata":"WMR","port":"1","city":"Analanjirofo, Madagascar"},{"bdrp":"MAROANTSETRA","iata":"WMN","port":"1","city":"Analanjirofo, Madagascar"},{"bdrp":"MALAGA","iata":"AGP","port":"1","city":"Andalucia Technology Park, Spain"},{"bdrp":"ESENBOGA","iata":"ESB","port":"1","city":"Ankara, Turkey"},{"bdrp":"ANQING TIANZHUSHAN","iata":"AQG","port":"1","city":"Anqing, China"},{"bdrp":"ANSHUN HUANGGUOSHU","iata":"AVA","port":"1","city":"Anshun, China"},{"bdrp":"ANTALYA","iata":"AYT","port":"1","city":"Antalya, Turkey"},{"bdrp":"IVATO","iata":"TNR","port":"1","city":"Antananarivo, Madagascar, Madagascar"},{"bdrp":"V. C. BIRD","iata":"ANU","port":"1","city":"Antigua and Barbuda, Antigua And Barbuda"},{"bdrp":"ARRACHART","iata":"DIE","port":"1","city":"Antsiranana, Madagascar"},{"bdrp":"AOMORI","iata":"AOJ","port":"1","city":"Aomori, Japan"},{"bdrp":"MONTERREY","iata":"MTY","port":"1","city":"Apodaca, Nuevo Leon, Mexico"},{"bdrp":"ARBA MINCH","iata":"AMH","port":"1","city":"Arba Minch, Ethiopia"},{"bdrp":"EAST LONDON","iata":"ELS","port":"1","city":"Arcadia, South Africa"},{"bdrp":"RODRIGUEZ BALLON","iata":"AQP","port":"1","city":"Arequipa, Peru"},{"bdrp":"COMANDANTE ARMANDO TOLA","iata":"FTE","port":"1","city":"Argentina, Argentina"},{"bdrp":"USHUAIA u2013 MALVINAS","iata":"USH","port":"1","city":"Argentina, Argentina"},{"bdrp":"TEXARKANA","iata":"TXK","port":"1","city":"Arkansas, United States"},{"bdrp":"RONALD REAGAN WASHINGTON","iata":"DCA","port":"1","city":"Arlington County, United States"},{"bdrp":"ARMIDALE","iata":"ARM","port":"1","city":"Armidale, Australia"},{"bdrp":"TOULOUSE BLAGNAC","iata":"TLS","port":"1","city":"Arnaud Bernard, France"},{"bdrp":"VLADIVOSTOK","iata":"VVO","port":"1","city":"Artyom, Russia"},{"bdrp":"QUEEN BEATRIX","iata":"AUA","port":"1","city":"Aruba, Aruba"},{"bdrp":"KILIMANJARO","iata":"JRO","port":"1","city":"Arusha, Tanzania"},{"bdrp":"ASAHIKAWA","iata":"AKJ","port":"1","city":"Asahikawa, Japan"},{"bdrp":"ASHGABAT","iata":"ASB","port":"1","city":"Ashgabat, Turkmenistan"},{"bdrp":"AUSTIN STRAUBEL","iata":"GRB","port":"1","city":"Ashwaubenon, United States"},{"bdrp":"ASOSA","iata":"ASO","port":"1","city":"Asosa, Ethiopia"},{"bdrp":"ASTANA","iata":"TSE","port":"1","city":"Astana, Kazakhstan"},{"bdrp":"ASTURIAS","iata":"OVD","port":"1","city":"Asturias, Spain"},{"bdrp":"SILVIO PETTIROSSI","iata":"ASU","port":"1","city":"Asuncion, Paraguay"},{"bdrp":"HALIWEN","iata":"ABU","city":"Atambua, Indonesia","port":"0"},{"bdrp":"ELEFTHERIOS VENIZELOS","iata":"ATH","port":"1","city":"Athens, Greece"},{"bdrp":"HARTSFIELD ATLANTA","iata":"ATL","port":"1","city":"Atlanta, United States"},{"bdrp":"TOLIARA","iata":"TLE","port":"1","city":"Atsimo-Andrefana, Madagascar, Madagascar"},{"bdrp":"AUCKLAND","iata":"AKL","port":"1","city":"Auckland, New Zealand"},{"bdrp":"AUSTIN","iata":"AUS","port":"1","city":"Austin, United States"},{"bdrp":"CLERMONT-FERRAND AUVERGNE","iata":"CFE","city":"Auvergne, France","port":"1"},{"bdrp":"AXUM","iata":"AXU","port":"1","city":"Axum, Ethiopia"},{"bdrp":"BALLINA BYRON","iata":"BNK","port":"1","city":"BALLINA BYRON, Australia"},{"bdrp":"BABO","iata":"BXB","port":"1","city":"Babo, Papua New Guinea"},{"bdrp":"BOCARAY","iata":"KLO","port":"1","city":"Bacacay, Philippines"},{"bdrp":"BACOLOD","iata":"BCD","port":"1","city":"Bacolod, Philippines"},{"bdrp":"BADAJOZ","iata":"BJZ","port":"1","city":"Badajoz, Spain"},{"bdrp":"BAGHDAD","iata":"BGW","port":"1","city":"Baghdad, Iraq"},{"bdrp":"BAHIR DAR","iata":"BJR","port":"1","city":"Bahar Dar, Ethiopia"},{"bdrp":"BAHAWALPUR","iata":"BHV","port":"1","city":"Bahawalpur, Pakistan"},{"bdrp":"SOA","iata":"BJW","city":"Bajawa, Indonesia","port":"0"},{"bdrp":"BAKELALAN","iata":"BKM","port":"1","city":"Bakelalan, Malaysia"},{"bdrp":"HEYDAR ALIYEV","iata":"GYD","port":"1","city":"Baku, Azerbaijan"},{"bdrp":"Sepinggan","iata":"BPN","city":"BalikPapan, Indonesia","port":"0"},{"bdrp":"QUETTA","iata":"UET","port":"1","city":"Balochistan, Pakistan, Pakistan"},{"bdrp":"BAMAKO u2013SENOU","iata":"BKO","port":"1","city":"Bamako, Mali"},{"bdrp":"CASSIDY","iata":"CXI","port":"1","city":"Banana, Kiribati"},{"bdrp":"SABANG","iata":"SBG","city":"Banda Aceh, Indonesia","port":"0"},{"bdrp":"Sultan Iskandar Muda","iata":"BTJ","city":"Banda Aceh, Indonesia","port":"0"},{"bdrp":"HUSEIN SASTRANEGARA","iata":"BDO","city":"Bandung, Indonesia","port":"0"},{"bdrp":"BANGALORE","iata":"BLR","port":"1","city":"Bangalore, India"},{"bdrp":"DON MUEANG","iata":"DMK","port":"1","city":"Bangkok - Don Mueang, Thailand"},{"bdrp":"SUVARNABHUMI","iata":"BKK","port":"1","city":"Bangkok, Thailand"},{"bdrp":"BANGUI M POKO","iata":"BGF","port":"1","city":"Bangui, Central African Republic"},{"bdrp":"SYAMSUDDIN NOOR","iata":"BDJ","city":"Banjarmasin, Indonesia","port":"0"},{"bdrp":"BLIMBINGSARI","iata":"BWX","city":"Banyuwangi, Indonesia","port":"0"},{"bdrp":"BAOSHAN YUNDUAN","iata":"BSD","port":"1","city":"Baoshan, China"},{"bdrp":"MADRID","iata":"MAD","port":"1","city":"Barajas, Spain"},{"bdrp":"MAASIN","iata":"PIA","port":"1","city":"Barangay Panan-awan, Philippines"},{"bdrp":"BARIO","iata":"BBN","port":"1","city":"Bario, Malaysia"},{"bdrp":"BERINGIN","iata":"MTW","city":"Barito Utara, Indonesia","port":"0"},{"bdrp":"BASRA","iata":"BSR","port":"1","city":"Basra, Iraq"},{"bdrp":"GOLDEN ROCK","iata":"SKB","port":"1","city":"Basseterre, Sri Lanka"},{"bdrp":"Hang Nadim","iata":"BTH","city":"Batam, Indonesia","port":"0"},{"bdrp":"BATON ROUGE METROPOLITAN","iata":"BTR","port":"1","city":"Baton Rouge, United States"},{"bdrp":"BATU LICIN","iata":"BTW","city":"Batu Licin, Indonesia","port":"0"},{"bdrp":"Baubau","iata":"BUW","city":"Baubau, Indonesia","port":"0"},{"bdrp":"TERRANCE B. LETTSOME","iata":"EIS","port":"1","city":"Beef Island, Bermuda"},{"bdrp":"BEIHAI FUCHENG","iata":"BHY","port":"1","city":"Beihai, China"},{"bdrp":"DATONG YUNGANG","iata":"DAT","port":"1","city":"Beijiazao, China"},{"bdrp":"BEIJING CAPITAL","iata":"PEK","port":"1","city":"Beijing, China"},{"bdrp":"BEIRUT u2013RAFIC HARIRI","iata":"BEY","port":"1","city":"Beirut, Lebanon"},{"bdrp":"BELGRADE NIKOLA TESLA","iata":"BEG","port":"1","city":"Belgrade, Serbia"},{"bdrp":"BEN GURION","iata":"TLV","port":"1","city":"Ben Gurion, Israel"},{"bdrp":"Fatmawati Soekarno","iata":"BKS","city":"Bengkulu, Indonesia","port":"0"},{"bdrp":"KALIMARAU","iata":"BEJ","city":"Berau, Indonesia","port":"0"},{"bdrp":"BERLIN TEGEL","iata":"TXL","port":"1","city":"Berlin, Germany"},{"bdrp":"FRANS KAISIEPO","iata":"BIK","city":"Biak, Indonesia","port":"0"},{"bdrp":"BILBAO","iata":"BIO","port":"1","city":"Bilbao, Spain"},{"bdrp":"BILLUND","iata":"BLL","port":"1","city":"Billund, Denmark"},{"bdrp":"BILOELA","iata":"ZBL","port":"1","city":"Biloela, Australia"},{"bdrp":"Muhammad Salahuddin","iata":"BMU","city":"Bima, Indonesia","port":"0"},{"bdrp":"BINTULU","iata":"BTU","port":"1","city":"Bintulu, Malaysia"},{"bdrp":"BIRMINGHAM","iata":"BHX","port":"1","city":"Birmingham, United Kingdom"},{"bdrp":"BIRMINGHAM","iata":"BHM","port":"1","city":"Birmingham, United States"},{"bdrp":"MANAS","iata":"FRU","port":"1","city":"Bishkek, Kyrgyzstan"},{"bdrp":"OSVALDO VIEIRA","iata":"OXB","port":"1","city":"Bissau, Guinea-Bissau"},{"bdrp":"BLACKALL","iata":"BKQ","port":"1","city":"Blackall, Australia"},{"bdrp":"CHILEKA","iata":"BLZ","port":"1","city":"Blantyre, Malawi"},{"bdrp":"BLOEMFONTEIN","iata":"BFN","port":"1","city":"Bloemfontein, South Africa"},{"bdrp":"LAS AMERICAS","iata":"SDQ","port":"1","city":"Boca Chica, Dominican Republic"},{"bdrp":"EL DORADO","iata":"BOG","port":"1","city":"Bogota, Colombia"},{"bdrp":"BOISE","iata":"BOI","port":"1","city":"Boise, United States"},{"bdrp":"GUGLIELMO MARCONI","iata":"BLQ","port":"1","city":"Bologna, Italy"},{"bdrp":"COPENHAGEN","iata":"CPH","port":"1","city":"Bopenhagen, Denmark"},{"bdrp":"LINCANG","iata":"LNJ","port":"1","city":"Boshang Town, China"},{"bdrp":"LOGAN","iata":"BOS","port":"1","city":"Boston, United States"},{"bdrp":"JOSE MARTI","iata":"HAV","port":"1","city":"Boyeros Municipality, Cuba"},{"bdrp":"DEPUTADO LUIS EDUARDO MAGALHAES","iata":"SSA","port":"1","city":"Brasil, Brazil"},{"bdrp":"BRASILIA","iata":"BSB","port":"1","city":"Brazil, Brazil"},{"bdrp":"MARECHAL CUNHA MACHADO","iata":"SLZ","port":"1","city":"Brazil, Brazil"},{"bdrp":"MARINGA","iata":"MGF","port":"1","city":"Brazil, Brazil"},{"bdrp":"PORTO SEGURO","iata":"BPS","port":"1","city":"Brazil, Brazil"},{"bdrp":"SANTAREM MAESTRO WILSON FONSECA","iata":"STM","port":"1","city":"Brazil, Brazil"},{"bdrp":"VAL DE CANS","iata":"BEL","port":"1","city":"Brazil, Brazil"},{"bdrp":"MAYA u2013MAYA","iata":"BZV","port":"1","city":"Brazzaville, Congo, The Democratic Republic Of The"},{"bdrp":"BREMEN","iata":"BRE","port":"1","city":"Bremen, Germany"},{"bdrp":"BRISBANE","iata":"BNE","port":"1","city":"Brisbane, Australia"},{"bdrp":"VIRGIN GORDA","iata":"VIJ","port":"1","city":"British Virgin Islands, United Kingdom"},{"bdrp":"BROOME","iata":"BME","port":"1","city":"Broome, Australia"},{"bdrp":"BRUNEI","iata":"BWN","port":"1","city":"Brunei, Brunei Darussalam"},{"bdrp":"BUCHAREST HENRI COANDA","iata":"OTP","port":"1","city":"Bucharest, Romania"},{"bdrp":"HENRI COANDA","iata":"BUH","port":"1","city":"Bucharest, Romania"},{"bdrp":"BUDAPEST FERENC LISZT","iata":"ROK","port":"1","city":"Budapest, Hungary"},{"bdrp":"LISZT FERENC","iata":"BUD","port":"1","city":"Budapest, Hungary"},{"bdrp":"BUJUMBURA","iata":"BJM","port":"1","city":"Bujumbura, Burundi"},{"bdrp":"ULSAN","iata":"USN","port":"1","city":"Buk District, Ulsan, South Korea"},{"bdrp":"BUKA","iata":"BUA","port":"1","city":"Buka Island, Papua New Guinea"},{"bdrp":"BULI","iata":"WUB","city":"Buli, Indonesia","port":"0"},{"bdrp":"BULOLO","iata":"BUL","port":"1","city":"Bulolo, Papua New Guinea"},{"bdrp":"BUNDABERG","iata":"BDB","port":"1","city":"Bundaberg, Australia"},{"bdrp":"MUARA BUNGO","iata":"MRB","city":"Bungo, Indonesia","port":"0"},{"bdrp":"POGUGOL","iata":"UOL","city":"Buol, Indonesia","port":"0"},{"bdrp":"BUON MA THUOT","iata":"BMV","port":"1","city":"Buon Ma Thuot, Vietnam"},{"bdrp":"PRINCE NAYEF BIN ABDULAZIZ","iata":"ELQ","port":"1","city":"Buraidah, Saudi Arabia"},{"bdrp":"BURBANK BOB HOPE","iata":"BUR","port":"1","city":"Burbank, United States"},{"bdrp":"GIMHAE","iata":"PUS","port":"1","city":"Busan, South Korea"},{"bdrp":"CANBERRA","iata":"CBR","port":"1","city":"CANBERRA, Australia"},{"bdrp":"CHRISTCHURCH","iata":"CHC","port":"1","city":"CHRISTCHURCH, New Zealand"},{"bdrp":"CABINDA AEROPORTO DE CABINDA","iata":"CAB","port":"1","city":"Cabinda, Angola"},{"bdrp":"CAIRNS","iata":"CNS","port":"1","city":"Cairns, Australia"},{"bdrp":"GENERAL LEOBARDO C. RUIZ","iata":"ZCL","port":"1","city":"Calera de Victor Rosales, Mexico"},{"bdrp":"CALGARY","iata":"YYC","port":"1","city":"Calgary, Canada"},{"bdrp":"MEADOWS FIELD","iata":"BFL","port":"1","city":"California, United States"},{"bdrp":"JORGE CHAVEZ","iata":"LIM","port":"1","city":"Callao, Peru"},{"bdrp":"FORT MCMURRAY","iata":"YMM","port":"1","city":"Canada, Canada"},{"bdrp":"REGINA","iata":"YQR","port":"1","city":"Canada, Canada"},{"bdrp":"ST. JOHNS INTERNATIONAL","iata":"YYT","port":"1","city":"Canada, Canada"},{"bdrp":"WINNIPEG JAMES ARMSTRONG RICHARDSON","iata":"YWG","port":"1","city":"Canada, Canada"},{"bdrp":"CANCUN","iata":"CUN","port":"1","city":"Cancun, Mexico"},{"bdrp":"LUIS MUNOZ MARIN","iata":"SJU","port":"1","city":"Carolina, Puerto Rico"},{"bdrp":"GERALD R. FORD","iata":"GRR","port":"1","city":"Cascade Charter Township, United States"},{"bdrp":"VINCENZO BELLINI","iata":"CTA","port":"1","city":"Catania, Italy"},{"bdrp":"CATUMBELA","iata":"CBT","port":"1","city":"Catumbela, Angola, Angola"},{"bdrp":"MACTAN-CEBU","iata":"CEB","port":"1","city":"Cebu, Philippines"},{"bdrp":"RALEIGH","iata":"RDU","port":"1","city":"Cedar Fork Township, Wake County, North Carolina, United States"},{"bdrp":"FRANCISCO SA CARNEIRO","iata":"OPO","port":"1","city":"Cedofeita, Portugal"},{"bdrp":"ROBERTS FIELD","iata":"RDM","port":"1","city":"Central Oregon, United States"},{"bdrp":"ARLANDA","iata":"STO","port":"1","city":"Central Stockholm, Sweden"},{"bdrp":"WASHINGTON DULLES","iata":"IAD","port":"1","city":"Centralia, United States"},{"bdrp":"LESTER B. PEARSON","iata":"YYZ","port":"1","city":"Centre Island, Canada"},{"bdrp":"CHANGDE TAOHUAYUAN","iata":"CGD","port":"1","city":"Changde, Hunan, China"},{"bdrp":"SHANGHAI HONGQIAO","iata":"SHA","port":"1","city":"Changning u2013Minhang, China"},{"bdrp":"CHANGSHA HUANGHUA","iata":"CSX","port":"1","city":"Changsha, China"},{"bdrp":"CHANGZHI WANGCUN","iata":"CIH","port":"1","city":"Changzhi, Shanxi, China, China"},{"bdrp":"CHANGZHOU BENNIU","iata":"CZX","port":"1","city":"Changzhou, China"},{"bdrp":"YANJI CHAOYANGCHUAN","iata":"YNJ","port":"1","city":"Chaoyangchuan Town, China"},{"bdrp":"CHARLEVILLE","iata":"CTL","port":"1","city":"Charleville, Australia"},{"bdrp":"CHARLOTTE DOUGLAS","iata":"CLT","port":"1","city":"Charlotte, United States"},{"bdrp":"CHARLOTTESVILLE-ALBEMARLE","iata":"CHO","port":"1","city":"Charlottesville, Virginia, United States"},{"bdrp":"CHATTANOOGA METROPOLITAN","iata":"CHA","port":"1","city":"Chattanooga, Tennessee, United States"},{"bdrp":"BUFFALO NIAGARA","iata":"BUF","port":"1","city":"Cheektowaga, United States"},{"bdrp":"YULIN YUYANG","iata":"UYN","port":"1","city":"Cheng County, China"},{"bdrp":"CHENGDU SHUANGLIU","iata":"CTU","port":"1","city":"Chengdu, China"},{"bdrp":"CHENNAI","iata":"MAA","port":"1","city":"Chennai, India"},{"bdrp":"CHEONGJU","iata":"CJJ","port":"1","city":"Cheongwon-gu, South Korea"},{"bdrp":"CHIANG MAI","iata":"CNX","port":"1","city":"Chiang Mai, Thailand"},{"bdrp":"MAE FAH LUANG-CHIANG RAI","iata":"CEI","port":"1","city":"Chiang Rai, Thailand"},{"bdrp":"CHICAGO OHARE","iata":"ORD","port":"1","city":"Chicago, United States"},{"bdrp":"GENERAL ROBERTO FIERRO VILLALOBOS","iata":"CUU","port":"1","city":"Chihuahua, Mexico"},{"bdrp":"CHINA BAY","iata":"TRR","port":"1","city":"China Bay, Sri Lanka"},{"bdrp":"CHITRAL","iata":"CJL","port":"1","city":"Chitral, Khyber-Pakhtunkhwa, Pakistan"},{"bdrp":"SHAH AMANAT","iata":"CGP","port":"1","city":"Chittagong, Bangladesh"},{"bdrp":"KHUDJAND","iata":"LBD","port":"1","city":"Chkalovsk, Tajikistan"},{"bdrp":"CHONGQING JIANGBEI","iata":"CKG","port":"1","city":"Chongqing, China"},{"bdrp":"GRANTLEY ADAMS","iata":"BGI","port":"1","city":"Christ Church, Barbados"},{"bdrp":"CHRISTMAS Island","iata":"XCH","port":"1","city":"Christmas Island, Christmas Island"},{"bdrp":"DUBROVNIK","iata":"DBV","port":"1","city":"Cilipi, Croatia"},{"bdrp":"LA ROMANA","iata":"LRM","port":"1","city":"City of La Romana, Dominican Republic"},{"bdrp":"CARRASCO","iata":"MVD","port":"1","city":"Ciudad de la Costa, Canelones, Uruguay, Uruguay"},{"bdrp":"CLARK","iata":"CRK","port":"1","city":"Clark, Philippines"},{"bdrp":"CLEVELAND HOPKINS","iata":"CLE","port":"1","city":"Cleveland, Ohio, United States"},{"bdrp":"CLONCURRY","iata":"CNJ","port":"1","city":"Cloncurry, Australia"},{"bdrp":"COFFS HARBOUR","iata":"CFS","port":"1","city":"Coffs Harbour, Australia"},{"bdrp":"COIMBATORE","iata":"CJB","port":"1","city":"Coimbatore, India"},{"bdrp":"EASTERWOOD","iata":"CLL","port":"1","city":"College Station, United States"},{"bdrp":"LYON","iata":"LYS","port":"1","city":"Colombier, France"},{"bdrp":"QUERETARO","iata":"QRO","port":"1","city":"Colon,El Marques, Mexico"},{"bdrp":"ALBANY","iata":"ALB","port":"1","city":"Colonie, United States"},{"bdrp":"COLORADO SPRINGS","iata":"COS","port":"1","city":"Colorado, United States"},{"bdrp":"DENVER","iata":"DEN","port":"1","city":"Colorado, United States"},{"bdrp":"COLUMBIA","iata":"COU","port":"1","city":"Columbia, United States"},{"bdrp":"PORT COLUMBUS","iata":"CMH","port":"1","city":"Columbus, United States"},{"bdrp":"CONAKRY","iata":"CKY","port":"1","city":"Conakry, Guinea"},{"bdrp":"TANCREDO NEVES","iata":"CNF","port":"1","city":"Confins, Brazil"},{"bdrp":"BRADLEY","iata":"BDL","port":"1","city":"Connecticut, United Kingdom"},{"bdrp":"CORK","iata":"ORK","port":"1","city":"Cork, Ireland"},{"bdrp":"CORPUS CHRISTI","iata":"CRP","port":"1","city":"Corpus Christi, United States"},{"bdrp":"COTE DAZUR","iata":"NCE","port":"1","city":"Cote Dazur, France"},{"bdrp":"COTONOU CADJEHOUN","iata":"COO","port":"1","city":"Cotonou Cadjehoun, Western Sahara"},{"bdrp":"COZUMEL","iata":"CZM","port":"1","city":"Cozumel, Mexico"},{"bdrp":"COASTAL CAROLINA","iata":"EWN","port":"1","city":"Craven County, United States"},{"bdrp":"LA CORUNA","iata":"LCG","port":"1","city":"Culleredo, Spain"},{"bdrp":"NOP GOLIAT ","iata":"DEX","city":"DEKAI, Indonesia","port":"0"},{"bdrp":"DUNEDIN","iata":"DUD","port":"1","city":"DUNEDIN, New Zealand"},{"bdrp":"DA NANG","iata":"DAD","port":"1","city":"Da Nang, Vietnam"},{"bdrp":"BIJIE FEIXIONG","iata":"BFJ","port":"1","city":"Dafang County, China"},{"bdrp":"LEOPOLD SEDAR SENGHOR","iata":"DKR","port":"1","city":"Dakar, Senegal"},{"bdrp":"DALAMAN","iata":"DLM","port":"1","city":"Dalaman, Turkey"},{"bdrp":"DALBANDIN","iata":"DBA","port":"1","city":"Dalbandin, Pakistan"},{"bdrp":"DALI","iata":"DLU","port":"1","city":"Dali, China"},{"bdrp":"DALIAN ZHOUSHUIZI","iata":"DLC","port":"1","city":"Dalian, China"},{"bdrp":"DALLAS LOVE FIELD","iata":"DAL","port":"1","city":"Dallas, United States"},{"bdrp":"FORT WORTH","iata":"DFW","port":"1","city":"Dallas, United States"},{"bdrp":"KING FAHD","iata":"DMM","port":"1","city":"Dammam, Saudi Arabia"},{"bdrp":"DANDONG LANGTOU","iata":"DDG","port":"1","city":"Dandong, China"},{"bdrp":"DAQING SARTU","iata":"DQA","port":"1","city":"Daqing, China"},{"bdrp":"DURHAM TEES VALLEY","iata":"MME","port":"1","city":"Darlington, United Kingdom"},{"bdrp":"DARU","iata":"DAU","port":"1","city":"Daru, Papua New Guinea"},{"bdrp":"DARWIN","iata":"DRW","port":"1","city":"Darwin, Australia"},{"bdrp":"DAVAO","iata":"DVO","port":"1","city":"Davao, Philippines"},{"bdrp":"DAYTON","iata":"DAY","port":"1","city":"Dayton, United States"},{"bdrp":"DAYTONA BEACH","iata":"DAB","port":"1","city":"Daytona Beach, United States"},{"bdrp":"ADDIS ABABA BOLE","iata":"ADD","port":"1","city":"Debre Zeyit, Ethiopia"},{"bdrp":"NGURAH RAI","iata":"DPS","city":"Denpasar, Bali, Indonesia","port":"0"},{"bdrp":"DERA GHAZI KHAN","iata":"DEA","port":"1","city":"Dera Ghazi Khan, Pakistan"},{"bdrp":"DERA ISMAIL KHAN","iata":"DSK","port":"1","city":"Dera Ismail Khan, Pakistan"},{"bdrp":"DES MOINES","iata":"DSM","port":"1","city":"Des Moines, United States"},{"bdrp":"DHAKA","iata":"DAC","port":"1","city":"Dhaka, Bangladesh"},{"bdrp":"MAWELLA LAGOON","iata":"DIW","port":"1","city":"Dickwella, Sri Lanka"},{"bdrp":"Presidente Nicolau Lobato","iata":"DIL","port":"1","city":"Dili, Timor-Leste"},{"bdrp":"YANGZHOU TAIZHOU","iata":"YTY","port":"1","city":"Dinggou, China"},{"bdrp":"ABA TENNA DEJAZMACH YILMA","iata":"DIR","port":"1","city":"Dire Dawa, Ethiopia"},{"bdrp":"DJIBOUTI u2013AMBOULI","iata":"JIB","port":"1","city":"Djibouti, Djibouti"},{"bdrp":"DOUGLAS u2013CHARLES","iata":"DOM","port":"1","city":"Dominica, Dominica"},{"bdrp":"SHEREMETYEVO","iata":"SVO","port":"1","city":"Domodedovo, Russia"},{"bdrp":"DAEGU","iata":"TAE","port":"1","city":"Dong District, Daegu, South Korea"},{"bdrp":"DONG HOI","iata":"VDH","port":"1","city":"Dong Hoi, Vietnam"},{"bdrp":"BAOTOU","iata":"BAV","port":"1","city":"Donghe District, China"},{"bdrp":"DOUALA","iata":"DLA","port":"1","city":"Douala, Cameroon"},{"bdrp":"BARCELONA","iata":"BCN","port":"1","city":"Downtown barcelona, Spain"},{"bdrp":"DRESDEN","iata":"DRS","port":"1","city":"Dresden Elbe Valley, Germany"},{"bdrp":"DUBAI","iata":"DXB","port":"1","city":"Dubai, United Arab Emirates"},{"bdrp":"DUBAI CITY BUS STATION","iata":"XNB","port":"1","city":"Dubai, United Arab Emirates"},{"bdrp":"DUBBO CITY","iata":"DBO","port":"1","city":"Dubbo, Australia"},{"bdrp":"DUBUQUE","iata":"DBQ","port":"1","city":"Dubuque, United States"},{"bdrp":"PINANG KAMPAI ","iata":"DUM","city":"Dumai, Riau, Indonesia","port":"0"},{"bdrp":"DUNHUANG","iata":"DNH","port":"1","city":"Dunhuang, China"},{"bdrp":"DURANGO PLATA COUNTY","iata":"DRO","port":"1","city":"Durango, United States"},{"bdrp":"KING SHAKA","iata":"DUR","port":"1","city":"Durban Central Business District, South Africa"},{"bdrp":"DUSHANBE I","iata":"DYU","port":"1","city":"Dushanbe, Tajikistan"},{"bdrp":"DUSSELFDORF","iata":"DUS","port":"1","city":"Dusselfdorf, Germany"},{"bdrp":"DZAOUDZI","iata":"DZA","port":"1","city":"Dzaoudzi, Mayotte"},{"bdrp":"LAGUARDIA","iata":"LGA","port":"1","city":"East Elmhurst, United States"},{"bdrp":"PUNTA CANA","iata":"PUJ","port":"1","city":"Eastern Dominican Repubic, Dominican Republic"},{"bdrp":"EASTERN IOWA","iata":"CID","port":"1","city":"Eastern Iowa, United States"},{"bdrp":"DYCE","iata":"ABZ","port":"1","city":"Edinbrugh, United Kingdom"},{"bdrp":"EDINBURGH","iata":"EDI","port":"1","city":"Edinbrugh, United Kingdom"},{"bdrp":"ORDOS EJIN HORO","iata":"DSN","port":"1","city":"Ejin Horo Banner, Mongolia"},{"bdrp":"EL ALTO","iata":"LPB","port":"1","city":"El Alto, Bolivia"},{"bdrp":"EL PASO","iata":"ELP","port":"1","city":"El Paso, United States"},{"bdrp":"ALICANTE u2013ELCHE","iata":"ALC","port":"1","city":"Elche, Spain"},{"bdrp":"ELDORET","iata":"EDL","port":"1","city":"Eldoret, Kenya"},{"bdrp":"ELMIRA","iata":"ELM","port":"1","city":"Elmira, United States"},{"bdrp":"H. Hasan Aroeboesman","iata":"ENE","city":"Ende, Indonesia","port":"0"},{"bdrp":"HALIFAX STANFIELD","iata":"YHZ","port":"1","city":"Enfield, Canada"},{"bdrp":"NORWICH","iata":"NWI","port":"1","city":"England, United Kingdom"},{"bdrp":"ENSHI XUJIAPING","iata":"ENH","port":"1","city":"Enshi City, China"},{"bdrp":"AKANU IBIAM","iata":"ENU","port":"1","city":"Enugu, Nigeria"},{"bdrp":"ERBIL","iata":"EBL","port":"1","city":"Erbil, Iraq"},{"bdrp":"ESPERANCE","iata":"EPR","port":"1","city":"Esperance, Australia"},{"bdrp":"PARIS ORLY","iata":"ORY","port":"1","city":"Essonne, France"},{"bdrp":"TALLINN","iata":"TLL","port":"1","city":"Estonia, Estonia"},{"bdrp":"EVANSVILLE","iata":"EVV","port":"1","city":"Evansville, United States"},{"bdrp":"LEARMONTH","iata":"LEA","port":"1","city":"Exmouth, Australia"},{"bdrp":"MINISTRO PISTARINI","iata":"EZE","port":"1","city":"Ezeiza, Argentina"},{"bdrp":"Fakfak","iata":"FKQ","city":"FakFak, Indonesia","port":"0"},{"bdrp":"HECTOR","iata":"FAR","port":"1","city":"Fargo, United States"},{"bdrp":"KUWAIT","iata":"KWI","port":"1","city":"Farwaniya, Kuwait"},{"bdrp":"BLUE GRASS","iata":"LEX","port":"1","city":"Fayette County, United States"},{"bdrp":"FAYETTEVILLE","iata":"FAY","port":"1","city":"Fayetteville, United States"},{"bdrp":"HEFEI XINQIAO","iata":"HFE","port":"1","city":"Feixi County, China"},{"bdrp":"TAMPERE PIRKKALA","iata":"TMP","port":"1","city":"Findland, Finland"},{"bdrp":"PITTSBURGH","iata":"PIT","port":"1","city":"Findlay \/Moon, United States"},{"bdrp":"DUBLIN","iata":"DUB","port":"1","city":"Finglas, Ireland"},{"bdrp":"TURKU","iata":"TKU","port":"1","city":"Finland, Finland"},{"bdrp":"VAASA","iata":"VAA","port":"1","city":"Finland, Finland"},{"bdrp":"FLAGSTAFF PULLIAM","iata":"FLG","port":"1","city":"Flagstaff, United States"},{"bdrp":"GALEAO","iata":"GIG","port":"1","city":"Flamengo Beach, Brazil"},{"bdrp":"BERGEN","iata":"BGO","port":"1","city":"Flesland,Hordaland, Norway"},{"bdrp":"BISHOP","iata":"FNT","port":"1","city":"Flint, United States"},{"bdrp":"FLORENCE","iata":"FLO","port":"1","city":"Florence County, United States"},{"bdrp":"FLORENCE PERETOLA","iata":"FLR","port":"1","city":"Florence, Italy"},{"bdrp":"GEWAYANTANA","iata":"LKA","city":"Flores Timur, Indonesia","port":"0"},{"bdrp":"NAPLES MUNICIPAL","iata":"APF","port":"1","city":"Florida, United States"},{"bdrp":"WAGGA WAGGA","iata":"WGA","port":"1","city":"Forest Hill, Australia"},{"bdrp":"KILLEEN HOOD","iata":"GRK","port":"1","city":"Fort Hood \/ Killeen, United States"},{"bdrp":"FORT SMITH","iata":"FSM","port":"1","city":"Fort Smith, United States"},{"bdrp":"DESTIN WALTON BEACH","iata":"VPS","port":"1","city":"Fort Walton Beach, United States"},{"bdrp":"FORT WAYNE","iata":"FWA","port":"1","city":"Fort Wayne, United States"},{"bdrp":"BORDEAUX MERIGNAC","iata":"BOD","port":"1","city":"France, France"},{"bdrp":"NANTES ATLANTIQUE","iata":"NTE","port":"1","city":"France, France"},{"bdrp":"STRASBOURG","iata":"SXB","port":"1","city":"France, France"},{"bdrp":"CHARLES DE GAULLE","iata":"CDG","port":"1","city":"Francourt, France"},{"bdrp":"FRANKFURT","iata":"FRA","port":"1","city":"Frankfurt, Germany"},{"bdrp":"GRAND BAHAMA","iata":"FPO","port":"1","city":"Freeport, Bahamas"},{"bdrp":"LUNGI","iata":"FNA","port":"1","city":"Freetown, Sierra Leone"},{"bdrp":"FRESNO YOSEMITE","iata":"FAT","port":"1","city":"Fresno, United States"},{"bdrp":"FUKUOKA","iata":"FUK","port":"1","city":"Fukuoka, Japan"},{"bdrp":"CHANGBAISHAN","iata":"NBS","port":"1","city":"Fusong County, China"},{"bdrp":"FUYANG XIGUAN","iata":"FUG","port":"1","city":"Fuyang, China"},{"bdrp":"FUZHOU CHANGLE","iata":"FOC","port":"1","city":"Fuzhou, China"},{"bdrp":"SIR SERETSE KHAMA ","iata":"GBE","port":"1","city":"Gaborone, Botswana"},{"bdrp":"GAINESVILLE","iata":"GNV","port":"1","city":"Gainesville, United States"},{"bdrp":"KOGGALA","iata":"KCT","port":"1","city":"Galle, Sri Lanka"},{"bdrp":"GAMBELA","iata":"GMB","port":"1","city":"Gambela, Ethiopia"},{"bdrp":"BANJUL","iata":"BJL","port":"1","city":"Gambia, Gambia"},{"bdrp":"GIMPO","iata":"GMP","port":"1","city":"Gangseo District, South Korea"},{"bdrp":"GANZHOU HUANGJIN","iata":"KOW","port":"1","city":"Ganzhou, China"},{"bdrp":"GAZIANTEP OGUZELI","iata":"GZT","port":"1","city":"Gaziantep, Turkey"},{"bdrp":"OWEN ROBERTS","iata":"GCM","port":"1","city":"George Town, Cayman Islands"},{"bdrp":"GEORGE","iata":"GRJ","port":"1","city":"George, South Africa"},{"bdrp":"AUGUSTA","iata":"AGS","port":"1","city":"Georgia, United States"},{"bdrp":"GERALDTON","iata":"GET","port":"1","city":"Geraldton, Australia"},{"bdrp":"GIBRALTAR","iata":"GIB","port":"1","city":"Gibraltar, Gibraltar"},{"bdrp":"GILGIT","iata":"GIL","port":"1","city":"Gilgit, Pakistan"},{"bdrp":"GISBORNE","iata":"GIS","port":"1","city":"Gisborne, New Zealand"},{"bdrp":"GLADSTONE","iata":"GLT","port":"1","city":"Gladstone, Australia"},{"bdrp":"GODE IDDIOLE","iata":"GDE","port":"1","city":"Gode, Ethiopia"},{"bdrp":"GOLD COAST","iata":"OOL","port":"1","city":"Gold Coast, Australia"},{"bdrp":"GONDAR","iata":"GDQ","port":"1","city":"Gondar, Ethiopia"},{"bdrp":"CAPE TOWN","iata":"CPT","port":"1","city":"Gondwana Game Reserve, South Africa"},{"bdrp":"LHASA GONGGAR","iata":"LXA","port":"1","city":"Gonggar County, China"},{"bdrp":"GOROKA","iata":"GKA","port":"1","city":"Goroka, Papua New Guinea"},{"bdrp":"Jalaluddin","iata":"GTO","city":"Gorontalo, Indonesia","port":"0"},{"bdrp":"LANDVETTER","iata":"GOT","port":"1","city":"Gothenburg, Sweden"},{"bdrp":"GOVE","iata":"GOV","port":"1","city":"Gove, Australia"},{"bdrp":"GRANADA","iata":"GRX","port":"1","city":"Granada, Spain"},{"bdrp":"TENERIFE SOUTH","iata":"TFS","port":"1","city":"Granadilla de Abona, Spain, Spain"},{"bdrp":"CENTRAL NEBRASKA","iata":"GRI","port":"1","city":"Grand Island, United States"},{"bdrp":"AKRON CANTON","iata":"CAK","port":"1","city":"Green, Ohio, United States"},{"bdrp":"PITT u2013GREENVILLE","iata":"PGV","port":"1","city":"Greenville, United States"},{"bdrp":"GREENVILLE u2013SPARTANBURG","iata":"GSP","port":"1","city":"Greer, United States"},{"bdrp":"MAURICE BISHOP","iata":"GND","port":"1","city":"Grenada, Grenada"},{"bdrp":"HONIARA","iata":"HIR","port":"1","city":"Guadalcanal, Solomon Islands"},{"bdrp":"DEL BAJIO","iata":"BJX","port":"1","city":"Guanajuato, Mexico"},{"bdrp":"GUANGZHOU BAIYUN","iata":"CAN","port":"1","city":"Guangzhou, China"},{"bdrp":"CUMBICA","iata":"GRU","port":"1","city":"Guarulhos, Brazil"},{"bdrp":"LA AURORA","iata":"GUA","port":"1","city":"Guatemala, Guatemala"},{"bdrp":"JOSE JOAQUIN DE OLMEDO","iata":"GYE","port":"1","city":"Guayaquil, Ecuador"},{"bdrp":"CHIZHOU JIUHUASHAN","iata":"JUH","port":"1","city":"Guichi District, China"},{"bdrp":"PIEDMONT TRIAD","iata":"GSO","port":"1","city":"Guilford County, United States"},{"bdrp":"GUILIN LIANGJIANG","iata":"KWL","port":"1","city":"Guilin, China"},{"bdrp":"GUIYANG LONGDONGBAO","iata":"KWE","port":"1","city":"Guiyang, China"},{"bdrp":"GULFPORT u2013BILOXI","iata":"GPT","port":"1","city":"Gulfport, United States"},{"bdrp":"Gunung Sitoli, Binaka","iata":"GNS","city":"GunungSitoli, Indonesia","port":"0"},{"bdrp":"GWADAR","iata":"GWD","port":"1","city":"Gwadar, Pakistan"},{"bdrp":"GWANGJU","iata":"KWJ","port":"1","city":"Gwangsan District, South Korea"},{"bdrp":"SAWYER","iata":"MQT","port":"1","city":"Gwinn, Michigan, United States"},{"bdrp":"HACHIJOJIMA","iata":"HAC","port":"1","city":"HACHIJIMA, Japan"},{"bdrp":"HAMILTON Island","iata":"HTI","port":"1","city":"HAMILTON Island, Australia"},{"bdrp":"HAYMAN Island","iata":"HIS","port":"1","city":"HAYMAN Island, Australia"},{"bdrp":"HONOLULU","iata":"HNL","port":"1","city":"HONOLULU, United States"},{"bdrp":"PRINCE SAID IBRAHIM","iata":"HAH","port":"1","city":"Hahaya, Comoros"},{"bdrp":"HAIKOU","iata":"HAK","port":"1","city":"Haikou, China"},{"bdrp":"HAI PHONG","iata":"HPH","port":"1","city":"Haiphong, Vietnam"},{"bdrp":"HAKODATE","iata":"HKD","port":"1","city":"Hakodate, Japan"},{"bdrp":"GAMARMALAMO","iata":"GLX","city":"Halmahera Utara, Indonesia","port":"0"},{"bdrp":"MATTALA RAJAPAKSA","iata":"HRI","port":"1","city":"Hambantota, Sri Lanka"},{"bdrp":"HAMBURG","iata":"HAM","port":"1","city":"Hamburg, Germany"},{"bdrp":"HAMI","iata":"HMI","port":"1","city":"Hami City, China"},{"bdrp":"HAMID KARZAI","iata":"KBL","port":"1","city":"Hamid Karzai, Afghanistan"},{"bdrp":"KJEVIK","iata":"KRS","port":"1","city":"Hamresanden, Norway"},{"bdrp":"HANDAN","iata":"HDG","port":"1","city":"Handan, China"},{"bdrp":"HANGZHOU XIAOSHAN","iata":"HGH","port":"1","city":"Hangzhou, China"},{"bdrp":"NOI BAI","iata":"HAN","port":"1","city":"Hanoi, Vietnam, Vietnam"},{"bdrp":"HARARE","iata":"HRE","port":"1","city":"Harare, Zimbabwe"},{"bdrp":"HARGEISA EGAL","iata":"HGA","port":"1","city":"Hargeisa Egal, Somalia"},{"bdrp":"VALLEY","iata":"BRO","port":"1","city":"Harlingen, United States"},{"bdrp":"HARRISBURG","iata":"MDT","port":"1","city":"Harrisburg, Pennsylvania, United States"},{"bdrp":"HAT YAI","iata":"HDY","port":"1","city":"Hat Yai, Thailand"},{"bdrp":"NORTHERN KENTUCKY","iata":"CVG","port":"1","city":"Hebron, United States"},{"bdrp":"HEIHE AIHUI","iata":"HEK","port":"1","city":"Heihe, China"},{"bdrp":"ZHENGZHOU XINZHENG","iata":"CGO","port":"1","city":"Hena - China, China"},{"bdrp":"MINNEAPOLIS u2013SAINT PAUL","iata":"MSP","port":"1","city":"Hennepin County, Minnesota, United States, United States"},{"bdrp":"HERAKLION","iata":"HER","port":"1","city":"Heraklion, Greece"},{"bdrp":"HERMOSILLO","iata":"HMO","port":"1","city":"Hermosillo, Mexico"},{"bdrp":"HERVEY BAY","iata":"HVB","port":"1","city":"Hervey Bay, Australia"},{"bdrp":"NORTHWEST ARKANSAS","iata":"XNA","port":"1","city":"Highfill, United States"},{"bdrp":"HILO","iata":"ITO","port":"1","city":"Hilo, United States"},{"bdrp":"HILTON HEAD","iata":"HHH","port":"1","city":"Hilton Head Island, United States"},{"bdrp":"TAN SON NHAT","iata":"SGN","port":"1","city":"Ho Chi Minh City, Vietnam"},{"bdrp":"HOBART","iata":"HBA","port":"1","city":"Hobart, Australia"},{"bdrp":"HOHHOT BAITA","iata":"HET","port":"1","city":"Hohhot, Mongolia"},{"bdrp":"FORT LAUDERDALE u2013HOLLYWOOD","iata":"FLL","port":"1","city":"Hollywood, United States"},{"bdrp":"HONG KONG","iata":"HKG","port":"1","city":"Hong Kong, Hong Kong"},{"bdrp":"HORN Island","iata":"HID","port":"1","city":"Horn Island, Australia"},{"bdrp":"HOTAN","iata":"HTN","port":"1","city":"Hotan, China"},{"bdrp":"BOUMEDIENNE","iata":"ALG","port":"1","city":"Houari boumedienne, Algeria"},{"bdrp":"GEORGE BUSH INTERCONTINENTAL","iata":"IAH","port":"1","city":"Houston, United States"},{"bdrp":"WILLIAM P. HOBBY","iata":"HOU","port":"1","city":"Houston, United States"},{"bdrp":"HUAIHUA ZHIJIANG","iata":"HJJ","port":"1","city":"Huaihua, China"},{"bdrp":"ALBANO MACHADO","iata":"NOV","port":"1","city":"Huambo, Angola"},{"bdrp":"XIAMEN GAOQI","iata":"XMN","port":"1","city":"Huli District, China"},{"bdrp":"TRI-STATE","iata":"HTS","port":"1","city":"Huntington, United States"},{"bdrp":"HUNTSVILLE","iata":"HSV","port":"1","city":"Huntsville, United States"},{"bdrp":"HURGHADA","iata":"HRG","port":"1","city":"Hurghada, Egypt"},{"bdrp":"XINING CAOJIABAO","iata":"XNN","port":"1","city":"Huzhu, China"},{"bdrp":"HYDERABAD","iata":"HYD","port":"1","city":"Hyderabad, India"},{"bdrp":"IWAKUNI","iata":"IWK","port":"1","city":"IWAKUNI, Japan"},{"bdrp":"OSHIMA","iata":"OIM","port":"1","city":"IZU OSHIMA, Japan"},{"bdrp":"IBIZA","iata":"IBZ","port":"1","city":"Ibiza, Spain"},{"bdrp":"MURTALA MUHAMMED","iata":"LOS","port":"1","city":"Ikeja, Nigeria"},{"bdrp":"IKI","iata":"IKI","port":"1","city":"Iki Island, Japan"},{"bdrp":"CENTRAL ILLINOIS","iata":"BMI","port":"1","city":"Illinois, United States"},{"bdrp":"Iloilo","iata":"ILO","port":"1","city":"Iloilo, Philippines"},{"bdrp":"CAIRO","iata":"CAI","port":"1","city":"Imbabah, Egypt"},{"bdrp":"SRI GURU RAM DAS JEE","iata":"ATQ","port":"1","city":"India, India"},{"bdrp":"INDIANAPOLIS","iata":"IND","port":"1","city":"Indianapolis, United States"},{"bdrp":"IPOH","iata":"IPH","port":"1","city":"Ipoh, Malaysia"},{"bdrp":"ATATURK","iata":"IST","port":"1","city":"Istanbul, Turkey"},{"bdrp":"CATARATAS","iata":"IGU","port":"1","city":"Itaipu Lake, Brazil"},{"bdrp":"TURIN","iata":"TRN","port":"1","city":"Italy, Italy"},{"bdrp":"OSAKA INTL ITAMI","iata":"ITM","port":"1","city":"Itami, Japan"},{"bdrp":"ITHACA TOMPKINS","iata":"ITH","port":"1","city":"Ithaca, United States"},{"bdrp":"JAIPUR","iata":"JAI","port":"1","city":"Jabalpur, India"},{"bdrp":"JACKSON u2013EVERS","iata":"JAN","port":"1","city":"Jackson, United States"},{"bdrp":"JACKSON u2013EVERS","iata":"JAN","port":"1","city":"Jackson, United States"},{"bdrp":"JACKSONVILLE","iata":"JAX","port":"1","city":"Jacksonville, United States"},{"bdrp":"SOEKARNO HATTA","iata":"CGK","city":"Jakarta - Cengkareng, Indonesia","port":"0"},{"bdrp":"HALIM PERDANAKUSUMA","iata":"HLP","city":"Jakarta - Halim, Indonesia","port":"0"},{"bdrp":"GUADALAJARA","iata":"GDL","port":"1","city":"Jalisco, Mexico"},{"bdrp":"Sultan Thaha Syaifuddin","iata":"DJB","city":"Jambi, Indonesia","port":"0"},{"bdrp":"Sentani","iata":"DJJ","city":"Jayapura, Indonesia","port":"0"},{"bdrp":"WAMENA","iata":"WMX","city":"Jayawijaya, Indonesia","port":"0"},{"bdrp":"AL MAKTOUM","iata":"DWC","port":"1","city":"Jebel Ali, United Arab Emirates"},{"bdrp":"KING ABDULAZIZ","iata":"JED","port":"1","city":"Jeddah, Saudi Arabia"},{"bdrp":"JEJU","iata":"CJU","port":"1","city":"Jeju Island, Jeju, South Korea"},{"bdrp":"NOTOHADINEGORO","iata":"JBB","city":"Jember, Indonesia","port":"0"},{"bdrp":"JIAMUSI DONGJIAO","iata":"JMU","port":"1","city":"Jiamusi, China"},{"bdrp":"NANCHANG CHANGBEI","iata":"KHN","port":"1","city":"Jiangxi China, China"},{"bdrp":"NANYANG JIANGYING","iata":"NNY","port":"1","city":"Jiangying, China"},{"bdrp":"JIXI XINGKAIHU","iata":"JXA","port":"1","city":"Jidong, China"},{"bdrp":"SHANTOU JIEYANG","iata":"SWA","port":"1","city":"Jiedong District, China"},{"bdrp":"WILWAL","iata":"JIJ","port":"1","city":"Jijiga, Ethiopia"},{"bdrp":"CHANGCHUN LONGJIA","iata":"CGQ","port":"1","city":"Jilin City, China"},{"bdrp":"ABA SEGUD","iata":"JIM","port":"1","city":"Jimma, Ethiopia"},{"bdrp":"XISHUANGBANNA GASA","iata":"JHG","port":"1","city":"Jinghong, China"},{"bdrp":"JINING QUFU","iata":"JNG","port":"1","city":"Jining, China"},{"bdrp":"QUANZHOU JINJIANG","iata":"JJN","port":"1","city":"Jinjiang, China"},{"bdrp":"JIUJIANG LUSHAN","iata":"JIU","port":"1","city":"Jiujiang, China"},{"bdrp":"SENAI","iata":"JHB","port":"1","city":"Johor Baru, Malaysia"},{"bdrp":"JOPLIN","iata":"JLN","port":"1","city":"Joplin, United States"},{"bdrp":"JUBA","iata":"JUB","port":"1","city":"Juba, Sudan"},{"bdrp":"INCA MANCO CAPAC","iata":"JUL","port":"1","city":"Juliaca, Peru"},{"bdrp":"INCA MANCO CAPAC","iata":"JUL","port":"1","city":"Juliaca, Peru"},{"bdrp":"JUNEAU","iata":"JNU","port":"1","city":"Juneau, United States"},{"bdrp":"KUSHIRO","iata":"KUH","port":"1","city":"KUSHIRO, Japan"},{"bdrp":"MOUNT","iata":"HGU","port":"1","city":"Kagamuga, Papua New Guinea"},{"bdrp":"KAGOSHIMA","iata":"KOJ","port":"1","city":"Kagoshima, Japan"},{"bdrp":"KAHULUI","iata":"OGG","port":"1","city":"Kahului, United States"},{"bdrp":"Kaimana, Utarom","iata":"KNG","city":"Kaimana, Indonesia","port":"0"},{"bdrp":"KONA","iata":"KOA","port":"1","city":"Kalaoa, United States"},{"bdrp":"KALGOORLIE-BOULDER","iata":"KGI","port":"1","city":"Kalgoorlie, Australia"},{"bdrp":"ENTEBBE","iata":"EBB","port":"1","city":"Kampala, Uganda"},{"bdrp":"YEAGER","iata":"CRW","port":"1","city":"Kanawha County, United States"},{"bdrp":"KOMATSU","iata":"KMQ","port":"1","city":"Kanazawa Shi, Japan"},{"bdrp":"KANSAS CITY","iata":"MCI","port":"1","city":"Kansas City, Missouri, United States, United States"},{"bdrp":"KAOHSIUNG","iata":"KHH","port":"1","city":"Kaohsiung, Taiwan, Taiwan"},{"bdrp":"PUTUSSIBAU","iata":"PSU","city":"Kapuas Hulu, Indonesia","port":"0"},{"bdrp":"JINNAH","iata":"KHI","port":"1","city":"Karachi, Pakistan"},{"bdrp":"KARAMAY","iata":"KRY","port":"1","city":"Karamay, China"},{"bdrp":"KAUNAS","iata":"SPI","port":"1","city":"Karmelava, Lituania, Lithuania"},{"bdrp":"KARRATHA","iata":"KTA","port":"1","city":"Karratha, Australia"},{"bdrp":"KASHGAR","iata":"KHG","port":"1","city":"Kashgar, Xinjiang, China, China"},{"bdrp":"SPLIT","iata":"SPU","port":"1","city":"Kastela, Croatia, Croatia"},{"bdrp":"TRIBHUVAN","iata":"KTM","port":"1","city":"Kathmandu, Nepal"},{"bdrp":"MOLOKAI","iata":"MKK","port":"1","city":"Kaunakakai, Hawaii, United States"},{"bdrp":"KAVIENG","iata":"KVG","port":"1","city":"Kavieng, Papua New Guinea"},{"bdrp":"O. R. TAMBO","iata":"JNB","port":"1","city":"Kempton Park, South Africa"},{"bdrp":"Haluoleo","iata":"KDI","city":"Kendari, Indonesia","port":"0"},{"bdrp":"DOBO","iata":"DOB","city":"Kepulauan Aru, Indonesia","port":"0"},{"bdrp":"KEPULAUAN COCOS","iata":"CCK","port":"1","city":"Kepulauan Cocos, Cocos (Keeling) Islands"},{"bdrp":"RAHADI OESMAN","iata":"KTG","city":"Ketapang, Indonesia","port":"0"},{"bdrp":"KETCHIKAN","iata":"KTN","port":"1","city":"Ketchikan, United States"},{"bdrp":"KEY WEST","iata":"EYW","port":"1","city":"Key West, United States"},{"bdrp":"KHABAROVSK NOVY","iata":"KHV","port":"1","city":"Khabarovsk, Russia"},{"bdrp":"KHARTOUM","iata":"KRT","port":"1","city":"Khartoum, Sudan"},{"bdrp":"KHON KAEN","iata":"KKC","port":"1","city":"Khon Kaen, Thailand, Thailand"},{"bdrp":"HUMBERSIDE","iata":"HUY","port":"1","city":"Kidlington, United Kingdom"},{"bdrp":"KIGALI","iata":"KGL","port":"1","city":"Kigali, Rwanda"},{"bdrp":"NORMAN MANLEY","iata":"KIN","port":"1","city":"Kingston, Jamaica, Jamaica"},{"bdrp":"KISUMU","iata":"KIS","port":"1","city":"Kisumu, Kenya, Kenya"},{"bdrp":"ODATE","iata":"ONJ","port":"1","city":"Kitaakita, Japan"},{"bdrp":"KITAKYUSHU","iata":"KKJ","port":"1","city":"Kitakyushu, Japan"},{"bdrp":"KIUNGA","iata":"UNG","port":"1","city":"Kiunga, Papua New Guinea"},{"bdrp":"KOBE","iata":"UKB","port":"1","city":"Kobe, Japan"},{"bdrp":"KOCHI","iata":"COK","port":"1","city":"Kochi, India"},{"bdrp":"SAMUI","iata":"USM","port":"1","city":"Koh Samui, Thailand"},{"bdrp":"NETAJI SUBHAS CHANDRA BOSEN","iata":"CCU","port":"1","city":"Kolkata, India"},{"bdrp":"KORLA","iata":"KRL","port":"1","city":"Korla, China"},{"bdrp":"SULTAN ISMAIL PETRA","iata":"KBR","port":"1","city":"Kota Bharu, Malaysia"},{"bdrp":"KOTA KINABALU","iata":"BKI","port":"1","city":"Kota Kinabalu, Malaysia"},{"bdrp":"Kotabaru","iata":"KBU","city":"Kotabaru, Indonesia","port":"0"},{"bdrp":"PANGKALAN BUN","iata":"PKN","city":"Kotawaringin Barat, Indonesia","port":"0"},{"bdrp":"KRABI","iata":"KBV","port":"1","city":"Krabi, Thailand"},{"bdrp":"DOMODEDOVO","iata":"DME","port":"1","city":"Krasnoselsky, Russia"},{"bdrp":"KUALA LUMPUR","iata":"KUL","port":"1","city":"Kuala Lumpur, Malaysia"},{"bdrp":"SULTAN MAHMUD","iata":"TGG","port":"1","city":"Kuala Terengganu, Malaysia"},{"bdrp":"SULTAN HAJI AHMAD SHAH","iata":"KUA","port":"1","city":"Kuantan, Malaysia"},{"bdrp":"KUCHING","iata":"KCH","port":"1","city":"Kuching, Malaysia"},{"bdrp":"KUDAT","iata":"KUD","port":"1","city":"Kudat, Malaysia"},{"bdrp":"KUITO","iata":"SVP","port":"1","city":"Kuito, Angola"},{"bdrp":"KUMAMOTO","iata":"KMJ","port":"1","city":"Kumamoto, Japan"},{"bdrp":"CHIMBU","iata":"CMU","port":"1","city":"Kundiawa, Papua New Guinea"},{"bdrp":"KUNMING WUJIABA","iata":"KMG","port":"1","city":"Kunming, China"},{"bdrp":"EAST KIMBERLEY","iata":"KNX","port":"1","city":"Kununurra, Australia"},{"bdrp":"El Tari","iata":"KOE","city":"Kupang, Indonesia","port":"0"},{"bdrp":"KUQA QIUCI","iata":"KCA","port":"1","city":"Kuqa, Xinjiang, China, China"},{"bdrp":"MELALAN","iata":"MLK","city":"Kutai Barat, Indonesia","port":"0"},{"bdrp":"LA CROSSE","iata":"LSE","port":"1","city":"La Crosse, United States"},{"bdrp":"RAMON VILLEDA MORALES","iata":"SAP","port":"1","city":"La Lima, Honduras"},{"bdrp":"LABUAN","iata":"LBU","port":"1","city":"Labuan, Malaysia"},{"bdrp":"Labuanbajo, Komodo","iata":"LBJ","city":"LabuanBajo, Indonesia","port":"0"},{"bdrp":"LABUHA, OESMAN SADIK","iata":"LAH","city":"Labuha, Indonesia","port":"0"},{"bdrp":"PHILIP S. W. GOLDSON","iata":"BZE","port":"1","city":"Ladyville, Belize"},{"bdrp":"LAE NADZAB","iata":"LAE","port":"1","city":"Lae, Papua New Guinea"},{"bdrp":"LAFAYETTE","iata":"LFT","port":"1","city":"Lafayette, United States"},{"bdrp":"LAHAD DATU","iata":"LDU","port":"1","city":"Lahad Datu, Malaysia"},{"bdrp":"ALLAMA IQBAL","iata":"LHE","port":"1","city":"Lahore, Pakistan"},{"bdrp":"LAKE CHARLES","iata":"LCH","port":"1","city":"Lake Charles, United States"},{"bdrp":"LALIBELA","iata":"LLI","port":"1","city":"Lalibela, Ethiopia"},{"bdrp":"LAMBERT ST.LOUIS","iata":"STL","port":"1","city":"Lambert St.Louis, Missouri, United States"},{"bdrp":"LAMPANG","iata":"LPT","port":"1","city":"Lampang, Thailand"},{"bdrp":"Radin Inten II","iata":"TKG","city":"Lampung, Indonesia","port":"0"},{"bdrp":"LANAI","iata":"LNY","port":"1","city":"Lanai City, United States"},{"bdrp":"EUGENE","iata":"EUG","port":"1","city":"Lane County, United States"},{"bdrp":"HANNOVER","iata":"HAJ","port":"1","city":"Langenhagen, Germany"},{"bdrp":"LANGKAWI","iata":"LGK","port":"1","city":"Langkawi, Malaysia"},{"bdrp":"LANZAROTE","iata":"ACE","port":"1","city":"Lanzarote, Spain"},{"bdrp":"LANZHOU ZHONGCHUAN","iata":"LHW","port":"1","city":"Lanzhou, China"},{"bdrp":"LUANG PRABANG","iata":"LPQ","port":"1","city":"Laos, Laos"},{"bdrp":"LAREDO","iata":"LRD","port":"1","city":"Laredo, United States"},{"bdrp":"LARNACA","iata":"LCA","port":"1","city":"Larnaca, Cyprus"},{"bdrp":"MCCARRAN","iata":"LAS","port":"1","city":"Las Vegas, United States"},{"bdrp":"LIBREVILLE LEON MBA","iata":"LBV","port":"1","city":"Lastourville, Gabon"},{"bdrp":"RIGA","iata":"RIX","port":"1","city":"Latvia, Latvia"},{"bdrp":"LAUNCESTON","iata":"LST","port":"1","city":"Launceston, Australia"},{"bdrp":"LAWAS","iata":"LWY","port":"1","city":"Lawas, Malaysia"},{"bdrp":"LAWTON SILL","iata":"LAW","port":"1","city":"Lawton, United States"},{"bdrp":"MARTINIQUE AIME CESAIRE","iata":"FDF","port":"1","city":"Le Lamentin, Martinique"},{"bdrp":"EDMONTON","iata":"YEG","port":"1","city":"Leduc County, Canada"},{"bdrp":"LEHIGH VALLEY","iata":"ABE","port":"1","city":"Lehigh Valley, United States"},{"bdrp":"COLUMBIAN METROPOLITAN","iata":"CAE","port":"1","city":"Lexington, United States"},{"bdrp":"Lhokseumawe, Malikussaleh","iata":"LSW","city":"Lhokseumawe, Indonesia","port":"0"},{"bdrp":"LIANYUNGANG BAITABU","iata":"LYG","port":"1","city":"Lianyungang, China"},{"bdrp":"LIBERIA","iata":"LIR","port":"1","city":"Liberia, Costa Rica"},{"bdrp":"LISBON","iata":"LIS","port":"1","city":"Liberty Avenue, Portugal"},{"bdrp":"LIBO A","iata":"LLB","port":"1","city":"Libo County, China"},{"bdrp":"LIHUE","iata":"LIH","port":"1","city":"Lihue, United States"},{"bdrp":"LIJIANG SANYI","iata":"LJG","port":"1","city":"Lijiang, China"},{"bdrp":"LILONGWE","iata":"LLW","port":"1","city":"Lilongwe, Malawi"},{"bdrp":"LIMBANG","iata":"LMN","port":"1","city":"Limbang, Malaysia"},{"bdrp":"YINCHUAN HEDONG","iata":"INC","port":"1","city":"Linghe, China"},{"bdrp":"LIPING","iata":"HZH","port":"1","city":"Liping, China"},{"bdrp":"LIUZHOU BAILIAN","iata":"LZH","port":"1","city":"Liuzhou, China"},{"bdrp":"LIVINGSTONE","iata":"LVI","port":"1","city":"Livingstone, Zambia"},{"bdrp":"Lombok","iata":"LOP","city":"Lombok, Mataram, Indonesia","port":"0"},{"bdrp":"LOME","iata":"LFW","port":"1","city":"Lome, Togo"},{"bdrp":"LIHIR Island","iata":"LNV","port":"1","city":"Londolovit, Papua New Guinea"},{"bdrp":"LONDON HEATHROW","iata":"LHR","port":"1","city":"London, United Kingdom"},{"bdrp":"LONG AKAH","iata":"LKH","port":"1","city":"Long Akah, Malaysia"},{"bdrp":"LONG BANGA","iata":"LBP","port":"1","city":"Long Banga, Malaysia"},{"bdrp":"LONG BEACH","iata":"LGB","port":"1","city":"Long Beach, United States"},{"bdrp":"LONG LELLANG","iata":"LGL","port":"1","city":"Long Lellang, Malaysia"},{"bdrp":"LONG SERIDAN","iata":"ODN","port":"1","city":"Long Seridan, Malaysia"},{"bdrp":"LONGREACH","iata":"LRE","port":"1","city":"Longreach, Australia"},{"bdrp":"EAST TEXAS","iata":"GGG","port":"1","city":"Longview, United States"},{"bdrp":"MOMOTE","iata":"MAS","port":"1","city":"Lorengau, Papua New Guinea"},{"bdrp":"LOS ANGELES","iata":"LAX","port":"1","city":"Los Angeles, United States"},{"bdrp":"ALEXANDRIA","iata":"AEX","port":"1","city":"Louisiana, United States"},{"bdrp":"LOUISVILLE","iata":"SDF","port":"1","city":"Louisville, United States"},{"bdrp":"QUATRO DE FEVEREIRO","iata":"LAD","port":"1","city":"Luanda, Angola"},{"bdrp":"LUBANGO","iata":"SDD","port":"1","city":"Lubango, Angola"},{"bdrp":"LUBBOCK PRESTON SMITH","iata":"LBB","port":"1","city":"Lubbock, United States"},{"bdrp":"SILAMPARI","iata":"LLG","city":"Lubuklinggau , Indonesia","port":"0"},{"bdrp":"LUBUMBASHI","iata":"FBM","port":"1","city":"Lubumbashi, Congo, The Democratic Republic Of The"},{"bdrp":"CHAUDHARY CHARAN SINGH","iata":"LKO","port":"1","city":"Lucknow, India"},{"bdrp":"LUENA","iata":"LUO","port":"1","city":"Luena, Angola"},{"bdrp":"LUGANO","iata":"LUG","port":"1","city":"Lugano, Switzerland"},{"bdrp":"MALTA","iata":"MLA","port":"1","city":"Luqa, Malta"},{"bdrp":"KENNETH KAUNDA","iata":"LUN","port":"1","city":"Lusaka, Zambia"},{"bdrp":"Syukuran Aminuddin Amir","iata":"LUW","city":"Luwuk, Indonesia","port":"0"},{"bdrp":"LUZHOU LANTIAN","iata":"LZO","port":"1","city":"Luzhou, China"},{"bdrp":"LYNCHBURG","iata":"LYH","port":"1","city":"Lynchburg, United States"},{"bdrp":"MEMANBETSU","iata":"MMB","port":"1","city":"MEMANBETSU, Japan"},{"bdrp":"MIYAKO","iata":"MMY","port":"1","city":"MIYAKO, Japan"},{"bdrp":"MONBETSU ","iata":"MBE","city":"MONBETSU , Indonesia","port":"0"},{"bdrp":"MACAU","iata":"MFM","port":"1","city":"Macau, Macau"},{"bdrp":"MACKAY","iata":"MKY","port":"1","city":"Mackay (Whitsundays), Australia"},{"bdrp":"ANTSIRABATO","iata":"ANM","port":"1","city":"Madagascar, Madagascar"},{"bdrp":"MADANG","iata":"MAG","port":"1","city":"Madang, Papua New Guinea"},{"bdrp":"HAMAD","iata":"DOH","port":"1","city":"Madinat Ash Shamal, Qatar"},{"bdrp":"DANE COUNTY","iata":"MSN","port":"1","city":"Madison, Wisconsin, United States"},{"bdrp":"MADURAI","iata":"IXM","port":"1","city":"Madurai, India"},{"bdrp":"AMBOROVY","iata":"MJN","port":"1","city":"Mahajanga, Madagascar, Madagascar"},{"bdrp":"BANGOR","iata":"BGR","port":"1","city":"Maine, United States"},{"bdrp":"SIMON BOLIVAR","iata":"CCS","port":"1","city":"Maiquetia, Venezuela"},{"bdrp":"SHIZUOKA","iata":"FSZ","port":"1","city":"Makinohara, Japan"},{"bdrp":"MALABO","iata":"SSG","port":"1","city":"Malabo, Equatorial Guinea"},{"bdrp":"Abdul Rachman Saleh","iata":"MLG","city":"Malang, Indonesia","port":"0"},{"bdrp":"MALANJE","iata":"MEG","port":"1","city":"Malanje, Angola, Angola"},{"bdrp":"MALE","iata":"MLE","port":"1","city":"Male, Malawi"},{"bdrp":"ROBERT ATTY BESSING","iata":"MLN","city":"Malinau, Indonesia","port":"0"},{"bdrp":"MALINDI","iata":"MYD","port":"1","city":"Malindi, Kenya"},{"bdrp":"OLILIT","iata":"SXK","city":"Maluku Tenggara Barat, Indonesia","port":"0"},{"bdrp":"MAMMOTH YOSEMITE","iata":"MMH","port":"1","city":"Mammoth Lakes, California, United States"},{"bdrp":"MAMUJU","iata":"MJU","city":"Mamuju, Indonesia","port":"0"},{"bdrp":"Sam Ratulangi","iata":"MDC","city":"Manado, Indonesia","port":"0"},{"bdrp":"AUGUSTO C. SANDINO","iata":"MGA","port":"1","city":"Managua, Nicaragua"},{"bdrp":"BAHRAIN","iata":"BAH","port":"1","city":"Manama, Bahrain"},{"bdrp":"SARASOTA BRADENTON","iata":"SRQ","port":"1","city":"Manatee \/ Sarasota counties, United States"},{"bdrp":"EDUARDO GOMES","iata":"MAO","port":"1","city":"Manaus, Brazil"},{"bdrp":"MANCHESTER","iata":"MAN","port":"1","city":"Manchester, British Indian Ocean Territory"},{"bdrp":"MANCHESTER u2013BOSTON","iata":"MHT","port":"1","city":"Manchester, New Hampshire, United States"},{"bdrp":"MANDALAY","iata":"MDL","port":"1","city":"Mandalay, Myanmar"},{"bdrp":"MANHATTAN","iata":"MHK","port":"1","city":"Manhattan, Kansas, United States"},{"bdrp":"NINOY AQUINO","iata":"MNL","port":"1","city":"Manila (NAIA), Philippines"},{"bdrp":"VALENCIA","iata":"VLC","port":"1","city":"Manises, Spain"},{"bdrp":"Rendani","iata":"MKW","city":"Manokwari, Indonesia","port":"0"},{"bdrp":"LA CHINITA","iata":"MAR","port":"1","city":"Maracaibo, Venezuela"},{"bdrp":"MARSEILLE PROVENCE","iata":"MRS","port":"1","city":"Marignane, France"},{"bdrp":"MARRAKESH MENARA","iata":"RAK","port":"1","city":"Marrakesh, Morocco"},{"bdrp":"MARSA ALAM","iata":"RMF","port":"1","city":"Marsa Alam, Egypt, Egypt"},{"bdrp":"MARUDI","iata":"MUR","port":"1","city":"Marudi, Sarawak, Malaysia"},{"bdrp":"BALTIMORE u2013WASHINGTON","iata":"BWI","port":"1","city":"Maryland, United States"},{"bdrp":"MASHHAD","iata":"MHD","port":"1","city":"Mashhad, Iran, Iran, Islamic Republic Of"},{"bdrp":"IWAMI","iata":"IWJ","port":"1","city":"Masuda, Japan"},{"bdrp":"MATSUYAMA","iata":"MYJ","port":"1","city":"Matsuyama, Japan"},{"bdrp":"WAI OTI","iata":"MOF","city":"Maumere, Indonesia","port":"0"},{"bdrp":"GENERAL RAFAEL BUELNA","iata":"MZT","port":"1","city":"Mazatla,Sinaloa, Mexico"},{"bdrp":"MCALLEN MILLER","iata":"MFE","port":"1","city":"McAllen, Texas, United States"},{"bdrp":"KUALA NAMU","iata":"KNO","city":"Medan - Kuala Namu, Indonesia","port":"0"},{"bdrp":"ROGUE VALLEYL u2013MEDFORD","iata":"MFR","port":"1","city":"Medford, Oregon, United States"},{"bdrp":"MOHAMMED V","iata":"CMN","port":"1","city":"Medina, Morocco"},{"bdrp":"MEDINA","iata":"MED","port":"1","city":"Medina, Saudi Arabia"},{"bdrp":"MEIXIAN","iata":"MXZ","port":"1","city":"Meixian, Meizhou, China"},{"bdrp":"ALULA ABA NEGA","iata":"MQX","port":"1","city":"Mekele, Ethiopia"},{"bdrp":"MALACCA","iata":"MKZ","port":"1","city":"Melaka, Malaysia"},{"bdrp":"MELBOURNE (ALLS)","iata":"VIZ","port":"1","city":"Melbourne (alls), Australia"},{"bdrp":"MELBOURNE","iata":"MEL","port":"1","city":"Melbourne, Australia"},{"bdrp":"MEMPHIS","iata":"MEM","port":"1","city":"Memphis, Tennessee, United States"},{"bdrp":"MORONDAVA","iata":"MOQ","port":"1","city":"Menabe, Madagascar, Madagascar"},{"bdrp":"MENDI","iata":"MDU","port":"1","city":"Mendi, Papua New Guinea"},{"bdrp":"LUOYANG BEIJIAO","iata":"LYA","port":"1","city":"Mengjin County, China"},{"bdrp":"MENONGUE","iata":"SPP","port":"1","city":"Menongue, Angola, Angola"},{"bdrp":"Mopah","iata":"MKQ","city":"Merauke, Indonesia","port":"0"},{"bdrp":"Meulaboh, Cut Nyak Dien","iata":"MEQ","city":"Meulaboh, Indonesia","port":"0"},{"bdrp":"MEXICO CITY","iata":"MEX","port":"1","city":"Mexico City, Mexico, Mexico"},{"bdrp":"GENEVE","iata":"GVA","port":"1","city":"Meyrin, Switzerland"},{"bdrp":"MIAMI","iata":"MIA","port":"1","city":"Miami-Dade County, Florida, United States"},{"bdrp":"MIANYANG NANJIAO","iata":"MIG","port":"1","city":"Mianyang, Sichuan, China, China"},{"bdrp":"KALAMAZOO \/BATTLE CREEK","iata":"AZO","port":"1","city":"Michigan, United States"},{"bdrp":"MORELIA","iata":"MLM","port":"1","city":"Michoacan, Mexico"},{"bdrp":"MIDLAND","iata":"MAF","port":"1","city":"Midland and Odessa, Texas, United States"},{"bdrp":"HIROSHIMA","iata":"HIJ","port":"1","city":"Mihara, Japan"},{"bdrp":"MALPENSA","iata":"MXP","port":"1","city":"Milan, Italy"},{"bdrp":"MILDURA","iata":"MQL","port":"1","city":"Mildura, Australia"},{"bdrp":"ERIE","iata":"ERI","port":"1","city":"Millcreek Township, United States"},{"bdrp":"MISIMA Island","iata":"MIS","port":"1","city":"Milne Bay, Papua New Guinea"},{"bdrp":"GENERAL MITCHELL","iata":"MKE","port":"1","city":"Milwaukee, Wisconsin, United States"},{"bdrp":"MINSK NATIONAL","iata":"MSQ","port":"1","city":"Minsk, Belarus"},{"bdrp":"MIRI","iata":"MYY","port":"1","city":"Miri, Malaysia"},{"bdrp":"GOLDEN TRIANGLE","iata":"GTR","port":"1","city":"Missisipi, United States"},{"bdrp":"MIYAZAKI A","iata":"KMI","port":"1","city":"Miyazaki, Japan"},{"bdrp":"MOBILE","iata":"MOB","port":"1","city":"Mobile, Alabama, United States"},{"bdrp":"MOHE GULIAN","iata":"OHE","port":"1","city":"Mohe, China"},{"bdrp":"MOENJODARO","iata":"MJD","port":"1","city":"Mohenjo-daro, Pakistan"},{"bdrp":"QUAD CITY","iata":"MLI","port":"1","city":"Moline, IL, United States"},{"bdrp":"MONACO HELIPORT","iata":"MCM","port":"1","city":"Monaco, Monaco"},{"bdrp":"MONROE (LOUISIANA)","iata":"MLU","port":"1","city":"Monroe, Louisiana, United States"},{"bdrp":"ROBERTS","iata":"ROB","port":"1","city":"Monrovia, Liberia"},{"bdrp":"SANGSTER","iata":"MBJ","port":"1","city":"Montego Bay, Jamaica, Jamaica"},{"bdrp":"MONTEREY","iata":"MRY","port":"1","city":"Monterey, California, United States"},{"bdrp":"MONTGOMERY","iata":"MGM","port":"1","city":"Montgomery, Alabama, United States"},{"bdrp":"MONTREAL ELLIOTT TRUDEAU","iata":"YUL","port":"1","city":"Montreal, Canada"},{"bdrp":"MORANBAH","iata":"MOV","port":"1","city":"Moranbah, Australia"},{"bdrp":"MOREE","iata":"MRZ","port":"1","city":"Moree, Australia"},{"bdrp":"MORO","iata":"MXH","port":"1","city":"Moro, Papua New Guinea, Papua New Guinea"},{"bdrp":"CENTRAL WISCONSIN","iata":"CWA","port":"1","city":"Mosinee, United States"},{"bdrp":"EXUMA","iata":"GGT","port":"1","city":"Moss Town, Bahamas"},{"bdrp":"MOUNT ISA","iata":"ISA","port":"1","city":"Mount Isa, Australia"},{"bdrp":"MAPUTO","iata":"MPM","port":"1","city":"Mozambique Island, Mozambique"},{"bdrp":"JULIUS NYERERE","iata":"DAR","port":"1","city":"Msasani Peninsula, Tanzania"},{"bdrp":"MUAN","iata":"MWX","port":"1","city":"Muan, South Jeolla Province, South Korea"},{"bdrp":"MUDANJIANG HAILANG","iata":"MDG","port":"1","city":"Mudanjiang, Heilongjiang, China, China"},{"bdrp":"MUKAH","iata":"MKM","port":"1","city":"Mukah, Sarawak, East Malaysia, Malaysia"},{"bdrp":"MULU","iata":"MZV","port":"1","city":"Mulu, Sarawak, Malaysia"},{"bdrp":"CHHATRAPATI SHIVAJI","iata":"BOM","port":"1","city":"Mumbai Maharashtra, India"},{"bdrp":"MUNICH","iata":"MUC","port":"1","city":"Munich, Germany"},{"bdrp":"MUSKAT","iata":"MCT","port":"1","city":"Muscat, Oman"},{"bdrp":"MWANZA","iata":"MWZ","port":"1","city":"Mwanza, Tanzania, Tanzania"},{"bdrp":"MYRTLE BEACH","iata":"MYR","port":"1","city":"Myrtle Beach, South Carolina, United States"},{"bdrp":"N DJILI","iata":"FIH","port":"1","city":"N djili, Congo, The Democratic Republic Of The"},{"bdrp":"NADI","iata":"NAN","port":"1","city":"NADI, Fiji"},{"bdrp":"Nabire","iata":"NBX","city":"Nabire, Indonesia","port":"0"},{"bdrp":"FUKUE","iata":"FUJ","port":"1","city":"Nagasaki, Japan"},{"bdrp":"NAGASAKI","iata":"NGS","port":"1","city":"Nagasaki, Japan"},{"bdrp":"NAGOYA CHUBU CENTRAIR","iata":"NGO","port":"1","city":"Nagoya, Japan"},{"bdrp":"JOMO KENYATTA","iata":"NBO","port":"1","city":"Nairobi Hill, Kenya"},{"bdrp":"NAKASHIBETSU","iata":"SHB","port":"1","city":"Nakashibetsu, Japan"},{"bdrp":"NAKHON PHANOM","iata":"KOP","port":"1","city":"Nakhon Phanom, Thailand"},{"bdrp":"NAKHON SI THAMMARAT","iata":"NST","port":"1","city":"Nakhon Si Thammarat, Thailand"},{"bdrp":"NAMIBE","iata":"MSZ","port":"1","city":"Namibe, Angola, Angola"},{"bdrp":"NAMPULA","iata":"APL","port":"1","city":"Nampula, Mozambique"},{"bdrp":"NANCHONG GAOPING","iata":"NAO","port":"1","city":"Nanchong, China"},{"bdrp":"NANJING","iata":"NKG","port":"1","city":"Nanjing, China"},{"bdrp":"KOCHI RYOMA","iata":"KCZ","port":"1","city":"Nankoku, Japan"},{"bdrp":"NANNING WUXU","iata":"NNG","port":"1","city":"Nanning, China"},{"bdrp":"YANCHENG NANYANG","iata":"YNZ","port":"1","city":"Nanyang, China"},{"bdrp":"NARATHIWAT","iata":"NAW","port":"1","city":"Narathiwat, Thailand"},{"bdrp":"LYNDEN PINDLING","iata":"NAS","port":"1","city":"Nassau, Bahamas"},{"bdrp":"RANAI","iata":"NTX","city":"Natuna, Indonesia","port":"0"},{"bdrp":"NDJAMENA","iata":"NDJ","port":"1","city":"Ndjamena, Chad"},{"bdrp":"SIMON MWANSA KAPWEPWE","iata":"NLA","port":"1","city":"Ndola, Zambia"},{"bdrp":"XISHUANGBANNA GASA","iata":"JHG","port":"1","city":"Near Gasa, China"},{"bdrp":"HARBIN TAIPING","iata":"HRB","port":"1","city":"Near The Town of Taiping, China"},{"bdrp":"JACK BROOKS","iata":"BPT","port":"1","city":"Nederland, United States"},{"bdrp":"FLAMINGO","iata":"BON","port":"1","city":"Netherlands, Netherlands"},{"bdrp":"HOSKINS","iata":"HKN","port":"1","city":"New Britain Island, Papua New Guinea"},{"bdrp":"INDIRA GANDHI","iata":"DEL","port":"1","city":"New Delhi, India"},{"bdrp":"TWEED NEW HAVEN","iata":"HVN","port":"1","city":"New Haven, United States"},{"bdrp":"LOUIS ARMSTRONG NEW ORLEANS","iata":"MSY","port":"1","city":"New Orleans, United States"},{"bdrp":"NEWCASTLE","iata":"NTL","port":"1","city":"New South Wales, Australia"},{"bdrp":"STEWART","iata":"SWF","port":"1","city":"New Windsor, United States"},{"bdrp":"GREATER BINGHAMTON","iata":"BGM","port":"1","city":"New York, United States"},{"bdrp":"JOHN F. KENNEDY","iata":"JFK","port":"1","city":"New York, United States"},{"bdrp":"SYRACUSE HANCOCK","iata":"SYR","port":"1","city":"New York, United States"},{"bdrp":"WATERTOWN","iata":"ART","port":"1","city":"New York, United States"},{"bdrp":"NEWARK LIBERTY","iata":"EWR","port":"1","city":"Newark, United States"},{"bdrp":"NEWMAN","iata":"ZNE","port":"1","city":"Newman, Australia"},{"bdrp":"NEWPORT NEWS \/WILLIAMSBURG","iata":"PHF","port":"1","city":"Newport News, United States"},{"bdrp":"NHA TRANG","iata":"CXR","port":"1","city":"Nha Trang, Vietnam"},{"bdrp":"DIORI HAMANI","iata":"NIM","port":"1","city":"Niamey, Niger"},{"bdrp":"PORT HARCOURT","iata":"PHC","port":"1","city":"Nigeria, Nigeria"},{"bdrp":"NIIGATA","iata":"KIJ","port":"1","city":"Niigata, Niigata, Japan"},{"bdrp":"NINGBO LISHE","iata":"NGB","port":"1","city":"Ningbo, China"},{"bdrp":"NORFOLK","iata":"ORF","port":"1","city":"Norfolk, United States"},{"bdrp":"ASHEVILLE","iata":"AVL","port":"1","city":"North Carolina, United States"},{"bdrp":"CHARLESTON","iata":"CHS","port":"1","city":"North Charleston, S.C, United States"},{"bdrp":"NORTH ELEUTHERA","iata":"ELH","port":"1","city":"North Eleuthera, Bahamas"},{"bdrp":"SAN DIEGO","iata":"SAN","port":"1","city":"North Harbor Drive San Diego, United States"},{"bdrp":"PORT LINCOLN","iata":"PLO","port":"1","city":"North Shields, Australia"},{"bdrp":"MELANGUANE","iata":"MNA","city":"North Sulawesi, Indonesia","port":"0"},{"bdrp":"GRAND JUNCTION","iata":"GJT","port":"1","city":"Northern Grand Junction, United States"},{"bdrp":"SAVANNAH \/HILTON HEAD","iata":"SAV","port":"1","city":"Northwest of The Central Business District of Savannah, United States"},{"bdrp":"ALESUND, VIGRA","iata":"AES","port":"1","city":"Norwegian, Norway"},{"bdrp":"SANDEFJORD","iata":"TRF","port":"1","city":"Norwegian, Norway"},{"bdrp":"TRONDHEIM, VAERNES","iata":"TRD","port":"1","city":"Norwegian, Norway"},{"bdrp":"FASCENE","iata":"NOS","port":"1","city":"Nosy Be, Madagascar"},{"bdrp":"ALEG","iata":"LEG","port":"1","city":"Nouakchott, Mauritania"},{"bdrp":"LINATE","iata":"MIL","port":"1","city":"Novegro, Italy"},{"bdrp":"NUNUKAN","iata":"NNX","city":"Nunukan, Indonesia","port":"0"},{"bdrp":"NUREMBERG","iata":"NUE","port":"1","city":"Nuremberg, Germany"},{"bdrp":"MOI","iata":"MBA","port":"1","city":"Nyali Beach, Kenya"},{"bdrp":"OAKLAND","iata":"OAK","port":"1","city":"Oakland, United States"},{"bdrp":"NOVOSIBIRSK TOLMACHEVO","iata":"OVB","port":"1","city":"Ob, Russia"},{"bdrp":"TOKACHI OBIHIRO ","iata":"OBO","city":"Obihiro, Indonesia","port":"0"},{"bdrp":"TOLEDO EXPRESS","iata":"TOL","port":"1","city":"Ohio, USA, United States"},{"bdrp":"OITA","iata":"OIT","port":"1","city":"Oita, Japan"},{"bdrp":"OKAYAMA","iata":"OKJ","port":"1","city":"Okayama, Japan"},{"bdrp":"OKINAWA, NAHA","iata":"OKA","port":"1","city":"Okinawa - Naha, Japan"},{"bdrp":"WILL ROGERS WORLD","iata":"OKC","port":"1","city":"Oklahoma City, United States"},{"bdrp":"OLBIA COSTA SMERALDA","iata":"OLB","port":"1","city":"Olbia, Italy"},{"bdrp":"OLYMPIC DAM","iata":"OLP","port":"1","city":"Olympic Dam, Australia"},{"bdrp":"EPPLEY AIRFIELD","iata":"OMA","port":"1","city":"Omaha, United States"},{"bdrp":"ONDJIVA PEREIRA","iata":"VPE","port":"1","city":"Ondjiva, Angola"},{"bdrp":"ORLANDO MELBOURNE","iata":"MLB","port":"1","city":"One Air Terminal Parkway Melbourne, Florida, United States"},{"bdrp":"OTTAWA MACDONALD u2013CARTIER","iata":"YOW","port":"1","city":"Ontario, Canada"},{"bdrp":"ONTARIO","iata":"ONT","port":"1","city":"Ontario, United States"},{"bdrp":"ORLANDO","iata":"MCO","port":"1","city":"Orlando, Florida, US, United States"},{"bdrp":"OSAKA","iata":"KIX","port":"1","city":"Osaka - Kansai, Japan"},{"bdrp":"OSH","iata":"OSS","port":"1","city":"Osh, Kyrgyzstan"},{"bdrp":"OUAGADOUGOU","iata":"OUA","port":"1","city":"Ouagadougou, Burkina Faso"},{"bdrp":"LA TONTOUTA","iata":"NOU","port":"1","city":"Pa, New Caledonia"},{"bdrp":"MINANGKABAU","iata":"PDG","city":"Padang, Indonesia","port":"0"},{"bdrp":"PAGO PAGO","iata":"PPG","port":"1","city":"Pago Pago, American Samoa, American Samoa"},{"bdrp":"MATAK","iata":"MWK","city":"Pal Matak, Kepulauan Riau, Indonesia","port":"0"},{"bdrp":"TJILIK RIWUT","iata":"PKY","city":"Palangka raya, Indonesia","port":"0"},{"bdrp":"Sultan Mahmud Badaruddin II","iata":"PLM","city":"Palembang, Indonesia","port":"0"},{"bdrp":"PALM BEACH","iata":"PBI","port":"1","city":"Palm Beach, United States"},{"bdrp":"PALM SPRINGS","iata":"PSP","port":"1","city":"Palm Springs, California, United States"},{"bdrp":"PALMA DE MALLORCA","iata":"PMI","port":"1","city":"Palma de Mallorca, Spain"},{"bdrp":"LONDON GATWICK","iata":"LGW","port":"1","city":"Palmers green, United Kingdom"},{"bdrp":"PALMASECA","iata":"CLO","port":"1","city":"Palmira, Colombia"},{"bdrp":"PALOPO LAGALIGO ","iata":"LLO","city":"Palopo Lagaligo , Indonesia","port":"0"},{"bdrp":"Mutiara","iata":"PLW","city":"Palu, Indonesia","port":"0"},{"bdrp":"NORTHWEST FLORIDA BEACHES","iata":"ECP","port":"1","city":"Panama, Panama"},{"bdrp":"DEPATI AMIR","iata":"PGK","city":"Pangkal pinang, Indonesia","port":"0"},{"bdrp":"PANJGUR","iata":"PJG","port":"1","city":"Panjgur, Pakistan"},{"bdrp":"FAAA","iata":"PPT","port":"1","city":"Papeete, French Polynesia"},{"bdrp":"PARABURDOO","iata":"PBO","port":"1","city":"Paraburdoo, Australia"},{"bdrp":"Sultan Syarif Kasim II","iata":"PKU","city":"Pekanbaru, Indonesia","port":"0"},{"bdrp":"PEMBA (MOZAMBIQUE)","iata":"POL","port":"1","city":"Pemba, Mozambique, Tanzania"},{"bdrp":"PENANG","iata":"PEN","port":"1","city":"Penang, Malaysia"},{"bdrp":"WILKES-BARRE","iata":"AVP","port":"1","city":"Pennsylvania, United States"},{"bdrp":"PENSACOLA","iata":"PNS","port":"1","city":"Pensacola, Florida, United States"},{"bdrp":"PERTH","iata":"PER","port":"1","city":"Perth, Australia"},{"bdrp":"BACHA KHAN","iata":"PEW","port":"1","city":"Peshawar, Pakistan"},{"bdrp":"SKOPJE","iata":"SKP","port":"1","city":"Petrovec, Macedonia, The Former Yugoslav Republic Of"},{"bdrp":"PHILADELPHIA","iata":"PHL","port":"1","city":"Philadelphia, United States"},{"bdrp":"PHNOM PENH","iata":"PNH","port":"1","city":"Phnom Penh, Cambodia"},{"bdrp":"PHOENIX SKY HARBOR","iata":"PHX","port":"1","city":"Phoenix, United States"},{"bdrp":"HUI","iata":"HUI","port":"1","city":"Phu Bai, Vietnam"},{"bdrp":"PHU CAT","iata":"UIH","port":"1","city":"Phu Cat, Vietnam"},{"bdrp":"PHU QUOC","iata":"PQC","port":"1","city":"Phu Quoc, Vietnam"},{"bdrp":"PHUKET","iata":"HKT","port":"1","city":"Phuket, Thailand"},{"bdrp":"PIARCO","iata":"POS","port":"1","city":"Piarco, Trinidad and Tobago"},{"bdrp":"GARDEN CITY","iata":"GCK","port":"1","city":"Pierceville Township, United States"},{"bdrp":"SIBOLGA","iata":"FLZ","city":"Pinangsori, Indonesia","port":"0"},{"bdrp":"PISA","iata":"PSA","port":"1","city":"Pisa, Italy, Italy"},{"bdrp":"SIR SEEWOOSAGUR RAMGOOLAM","iata":"MRU","port":"1","city":"Plaine Magnien, Mauritius"},{"bdrp":"POHANG","iata":"KPO","port":"1","city":"Pohang, South Korea"},{"bdrp":"POINTE NOIRE","iata":"PNR","port":"1","city":"Pointe Noire, Congo"},{"bdrp":"POINTE VELE","iata":"FUT","port":"1","city":"Pointe Vele, Wallis And Futuna"},{"bdrp":"Sangia Nibandera Pomalaa","iata":"PUM","city":"Pomalaa, Indonesia","port":"0"},{"bdrp":"SUPADIO","iata":"PNK","city":"Pontianak, Indonesia","port":"0"},{"bdrp":"GIRUA","iata":"PNP","port":"1","city":"Popondetta, Papua New Guinea"},{"bdrp":"PORT BOUET","iata":"ABJ","port":"1","city":"Port Bouet, Brazil"},{"bdrp":"PORT HEDLAND","iata":"PHE","port":"1","city":"Port Hedland, Australia"},{"bdrp":"PORT MACQUARIE","iata":"PQQ","port":"1","city":"Port Macquarie, Australia"},{"bdrp":"BAUERFIELD","iata":"VLI","port":"1","city":"Port Vila, Vanuatu"},{"bdrp":"GEORGE BEST BELFAST CITY","iata":"BHD","port":"1","city":"Port of Belfast, Ireland"},{"bdrp":"PORTLAND","iata":"PWM","port":"1","city":"Portland, Maine, United States"},{"bdrp":"PORTLAND","iata":"PDX","port":"1","city":"Portland, United States"},{"bdrp":"SALGADO FILHO","iata":"POA","port":"1","city":"Porto Alegre, Brazil"},{"bdrp":"COLOGNE BONN","iata":"CGN","port":"1","city":"Porz, Germany"},{"bdrp":"Poso, Kasiguncu","iata":"PSJ","city":"Poso, Indonesia","port":"0"},{"bdrp":"T. F. GREEN","iata":"PVD","port":"1","city":"Post Road Warwick, Rhode Island, United States"},{"bdrp":"RUZYNE","iata":"PRG","port":"1","city":"Prague 1, Czech Republic"},{"bdrp":"NELSON MANDELA","iata":"RAI","port":"1","city":"Praia, Cape Verde, South Africa"},{"bdrp":"GLASGOW","iata":"GLA","port":"1","city":"Prestwick, United Kingdom"},{"bdrp":"PROVIDENCIALES","iata":"PLS","port":"1","city":"Providenciales, Turks and Caicos Islands, United States Minor Outlying Islands"},{"bdrp":"COMODORO ARTURO MERINO BENITEZ","iata":"SCL","port":"1","city":"Pudahuel, Chile"},{"bdrp":"PUEBLA","iata":"PBC","port":"1","city":"Puebla, Mexico"},{"bdrp":"PUER SIMAO","iata":"SYM","port":"1","city":"Puer, Yunnan, China"},{"bdrp":"EL TEPUAL","iata":"PMC","port":"1","city":"Puerto Montt, Chile"},{"bdrp":"GREGORIO LUPERON","iata":"POP","port":"1","city":"Puerto Plata, Dominican Republic"},{"bdrp":"Puerto Princesa","iata":"PPS","port":"1","city":"Puerto Princesa, Philippines"},{"bdrp":"LICENCIADO GUSTAVO DIAZ ORDAZ","iata":"PVR","port":"1","city":"Puerto Vallarta, Jalisco, Mexico"},{"bdrp":"FUERTEVENTURA","iata":"FUE","port":"1","city":"Puerto del Rosario, Spain"},{"bdrp":"CLINTON","iata":"LIT","port":"1","city":"Pulaski County, United States"},{"bdrp":"MOROTAI","iata":"OTI","city":"Pulau Morotai, Indonesia","port":"0"},{"bdrp":"FAISALABAD","iata":"LYP","port":"1","city":"Punjab, Pakistan"},{"bdrp":"MULTAN","iata":"MUX","port":"1","city":"Punjab, Pakistan, Pakistan"},{"bdrp":"PRESIDENTE CARLOS IBANEZ DEL CAMPO","iata":"PUQ","port":"1","city":"Punta Arenas,chile, Chile"},{"bdrp":"QIANJIANG WULINGSHAN","iata":"JIQ","port":"1","city":"Qianjiang, China"},{"bdrp":"QINGDAO","iata":"TAO","port":"1","city":"Qingdao, China"},{"bdrp":"QIQIHAR SANJIANZI","iata":"NDG","port":"1","city":"Qiqihar, China"},{"bdrp":"QUEBEC CITY JEAN LESAGE","iata":"YQB","port":"1","city":"Quebec City, Canada"},{"bdrp":"QUEEN ALIA","iata":"AMM","port":"1","city":"Queen Alia , Jordan"},{"bdrp":"WHITSUNDAY COAST - PROSERPINE","iata":"PPP","port":"1","city":"Queensland Australia, Australia"},{"bdrp":"BARCALDINE","iata":"BCI","port":"1","city":"Queensland, Australia"},{"bdrp":"EMERALD","iata":"EMD","port":"1","city":"Queensland, Australia"},{"bdrp":"QUEENSTOWN","iata":"ZQN","port":"1","city":"Queenstown, New Zealand"},{"bdrp":"RABAUL","iata":"RAB","port":"1","city":"Rabaul, Papua New Guinea"},{"bdrp":"SHAIKH ZAYED","iata":"RYK","port":"1","city":"Rahim Yar Khan, Pakistan"},{"bdrp":"MARINDA","iata":"RJM","city":"Raja Ampat, Indonesia","port":"0"},{"bdrp":"RAPID CITY","iata":"RAP","port":"1","city":"Rapid City, South Dakota, United States"},{"bdrp":"RAROTONGA","iata":"RAR","port":"1","city":"Rarotonga, Cook Islands"},{"bdrp":"RAVENSTHORPE","iata":"RVT","port":"1","city":"Ravensthorpe, Australia"},{"bdrp":"BENAZIR BHUTTO","iata":"ISB","port":"1","city":"Rawalpindi, Pakistan"},{"bdrp":"RECIFE \/GUARARAPES FREYRE","iata":"REC","port":"1","city":"Recife, Brazil"},{"bdrp":"RENO u2013TAHOE","iata":"RNO","port":"1","city":"Reno, Nevada, United States"},{"bdrp":"JAMES SPRIGGS PAYNE","iata":"MLW","port":"1","city":"Republic Of Liberia, Liberia"},{"bdrp":"ALBERT J. ELLIS","iata":"OAJ","port":"1","city":"Richlands, United States"},{"bdrp":"VANCOUVER","iata":"YVR","port":"1","city":"Richmond, Canada"},{"bdrp":"JOSE MARIA CORDOVA","iata":"MDE","port":"1","city":"Rionegro, Colombia"},{"bdrp":"KING KHALID","iata":"RUH","port":"1","city":"Riyadh, Saudi Arabia"},{"bdrp":"ROANOKE u2013BLACKSBURG","iata":"ROA","port":"1","city":"Roanoke, Virginia, United States, United States"},{"bdrp":"JUAN MANUEL GALVEZ","iata":"RTB","port":"1","city":"Roatan, Honduras"},{"bdrp":"ROCHESTER","iata":"RST","port":"1","city":"Rochester, Minnesota, United States"},{"bdrp":"GREATER ROCHESTER","iata":"ROC","port":"1","city":"Rochester, New York, United States"},{"bdrp":"ROMA","iata":"RMA","port":"1","city":"Roma, Australia"},{"bdrp":"FIUMICINO","iata":"FCO","port":"1","city":"Rome, Italy"},{"bdrp":"DETROIT METROPOLITAN","iata":"DTW","port":"1","city":"Romulus, United States"},{"bdrp":"LONG Island MACARTHUR","iata":"ISP","port":"1","city":"Ronkonkoma, United States"},{"bdrp":"ROSWELL INTERNATIONAL AIR CENTER","iata":"ROW","port":"1","city":"Roswell, New Mexico, United States"},{"bdrp":"LEKUNIK","iata":"RTI","city":"Rote Ndao, Indonesia","port":"0"},{"bdrp":"ROTTERDAM THE HAGUE","iata":"RTM","port":"1","city":"Rotterdam, Netherlands"},{"bdrp":"FRANS SALES LEGA","iata":"RTG","city":"Ruteng, Indonesia","port":"0"},{"bdrp":"SAGA","iata":"HSG","port":"1","city":"SAGA, Japan"},{"bdrp":"SIMEULEU","iata":"SMG","city":"SIMEULEU, Indonesia","port":"0"},{"bdrp":"SACHEON","iata":"HIN","port":"1","city":"Sacheon, South Korea"},{"bdrp":"SACRAMENTO","iata":"SMF","port":"1","city":"Sacramento, United States"},{"bdrp":"SIALKOT","iata":"SKT","port":"1","city":"Sahiwal, Pakistan"},{"bdrp":"PRINCESS JULIANA","iata":"SXM","port":"1","city":"Saint Martin, Netherlands"},{"bdrp":"CYRIL E. KING","iata":"STT","port":"1","city":"Saint Thomas, U.S, United States"},{"bdrp":"EUROA BASEL MULHOUSE FREIBURG","iata":"BSL","port":"1","city":"Saint-Louis France, France"},{"bdrp":"SAINTE MARIE","iata":"SMS","port":"1","city":"Sainte Marie, Madagascar"},{"bdrp":"ROLAND GARROS","iata":"RUN","port":"1","city":"Sainte-Marie on Reunion, France"},{"bdrp":"SAIPAN","iata":"SPN","port":"1","city":"Saipan, United States"},{"bdrp":"SHONAI","iata":"SYO","port":"1","city":"Sakata, Japan"},{"bdrp":"AMILCAR CABRAL","iata":"SAL","port":"1","city":"Sal, Cape Verde, Cape Verde"},{"bdrp":"WICOMICO","iata":"SBY","port":"1","city":"Salisbury, Maryland, United States"},{"bdrp":"SALT LAKE CITY","iata":"SLC","port":"1","city":"Salt Lake City, United States"},{"bdrp":"TEMINDUNG","iata":"AAP","city":"Samarinda, Indonesia","port":"0"},{"bdrp":"FALEOLO","iata":"APW","port":"1","city":"Samoa, Samoa"},{"bdrp":"H. Asan Sampit","iata":"SMQ","city":"Sampit, Indonesia","port":"0"},{"bdrp":"SAN ANGELO","iata":"SJT","port":"1","city":"San Angelo, United States"},{"bdrp":"SAN ANTONIO","iata":"SAT","port":"1","city":"San Antonio, Texas, US, United States"},{"bdrp":"TENERIFE NORTH","iata":"TFN","port":"1","city":"San Cristobal de La Laguna, Spain"},{"bdrp":"SAN CRISTOBAL","iata":"SCY","port":"1","city":"San Cristobal, Ecuador"},{"bdrp":"SAN FRANSISCO","iata":"SFO","port":"1","city":"San Francisco, United States"},{"bdrp":"LOS CABOS","iata":"SJD","port":"1","city":"San Jose del Cabo, Mexico"},{"bdrp":"SAN JOSE","iata":"SJC","port":"1","city":"San Jose, United States"},{"bdrp":"SAN LUIS OBISPO COUNTY","iata":"SBP","port":"1","city":"San Luis Obispo, California, United States"},{"bdrp":"PONCIANO ARRIAGA","iata":"SLP","port":"1","city":"San Luis Potos, Mexico"},{"bdrp":"SANAA","iata":"SAH","port":"1","city":"Sana A, Yemen"},{"bdrp":"SANDAKAN","iata":"SDK","port":"1","city":"Sandaka, Malaysia"},{"bdrp":"RICHMOND","iata":"RIC","port":"1","city":"Sandston, Virginia, United States"},{"bdrp":"LUXEMBOURG FINDEL","iata":"LUX","port":"1","city":"Sandweiler, Luxembourg"},{"bdrp":"JOHN WAYNE","iata":"SNA","port":"1","city":"Santa Ana, United States"},{"bdrp":"SANTA BARBARA MUNICIPAL","iata":"SBA","port":"1","city":"Santa Barbara, California, United States, United States"},{"bdrp":"VIRU VIRU","iata":"VVI","port":"1","city":"Santa Cruz de la Sierra, Bolivia"},{"bdrp":"MADEIRA","iata":"FNC","port":"1","city":"Santa Cruz, Portugal"},{"bdrp":"SANTA FE MUNICIPAL","iata":"SAF","port":"1","city":"Santa Fe, New Mexico, United States"},{"bdrp":"CIBAO","iata":"STI","port":"1","city":"Santiago Dominican Republic, Dominican Republic"},{"bdrp":"SANTIAGO DE COMPOSTELA","iata":"SCQ","port":"1","city":"Santiago de Compostela, Spain"},{"bdrp":"SANYA PHOENIX","iata":"SYX","port":"1","city":"Sanya, Hainan, China"},{"bdrp":"ZHUHAI JINWAN","iata":"ZUH","port":"1","city":"Sanzao Town, China"},{"bdrp":"AFONSO PENA","iata":"CWB","port":"1","city":"Sao Jose Dos Pinhais, Brazil"},{"bdrp":"SAO TOME","iata":"TMS","port":"1","city":"Sao Tome, Sao Tome And Principe"},{"bdrp":"SAPPORO","iata":"CTS","port":"1","city":"Sapporo - Shin-Chitose, Japan"},{"bdrp":"JACKSONS","iata":"POM","port":"1","city":"Saraga, Papua New Guinea"},{"bdrp":"SAURIMO","iata":"VHC","port":"1","city":"Saurimo, Angola"},{"bdrp":"SAMBAVA","iata":"SVB","port":"1","city":"Sava Region, Madagascar"},{"bdrp":"VIENNA","iata":"VIE","port":"1","city":"Schwechat, Austria"},{"bdrp":"SEATTLE TACOMA","iata":"SEA","port":"1","city":"Seattle, United States"},{"bdrp":"MILAN LINATE","iata":"LIN","port":"1","city":"Segrate, Italy"},{"bdrp":"SELAYAR","iata":"YKR","city":"Selayar, Indonesia","port":"0"},{"bdrp":"Achmad Yani","iata":"SRG","city":"Semarang, Indonesia","port":"0"},{"bdrp":"SEMERA","iata":"SZE","port":"1","city":"Semien Mountains National Park, Ethiopia"},{"bdrp":"SENDAI","iata":"SDJ","port":"1","city":"Sendai, Japan"},{"bdrp":"INCHEON","iata":"ICN","port":"1","city":"Seoul, South Korea"},{"bdrp":"SEVILLE","iata":"SVQ","port":"1","city":"Seville, Spain"},{"bdrp":"SHANGHAI PUDONG","iata":"PVG","port":"1","city":"Shanghai, China"},{"bdrp":"DIQING SHANGRI-LA","iata":"DIG","port":"1","city":"Shangri-La, China"},{"bdrp":"SHARJAH","iata":"SHJ","port":"1","city":"Sharjah, United Arab Emirates"},{"bdrp":"SHENYANG","iata":"SHE","port":"1","city":"Shenyang, China"},{"bdrp":"Shenzhen","iata":"SZX","port":"1","city":"Shenzhen, China"},{"bdrp":"NEW ISHIGAKI","iata":"ISG","port":"1","city":"Shiraho, Japan"},{"bdrp":"SHIRE","iata":"SHC","port":"1","city":"Shire, Ethiopia"},{"bdrp":"SHREVEPORT","iata":"SHV","port":"1","city":"Shreveport, United States"},{"bdrp":"XUZHOU GUANYIN","iata":"XUZ","port":"1","city":"Shuanggou, China"},{"bdrp":"SUNAN SHUOFANG","iata":"WUX","port":"1","city":"Shuofang Subdistrict, China"},{"bdrp":"SIBU","iata":"SBW","port":"1","city":"Sibu, Malaysia"},{"bdrp":"SIEM REAP","iata":"REP","port":"1","city":"Siem Reap, Cambodia"},{"bdrp":"SIGIRIYA","iata":"GIU","port":"1","city":"Sigiriya, Sri Lanka"},{"bdrp":"STOCKHOLM ARLANDA","iata":"ARN","port":"1","city":"Sigtuna, Sweden"},{"bdrp":"Silangit","iata":"DTB","city":"Silangit, Indonesia","port":"0"},{"bdrp":"LONDON CITY","iata":"LCY","port":"1","city":"Silvertown, United Kingdom"},{"bdrp":"CHANGI","iata":"SIN","port":"1","city":"Singapore, Singapore"},{"bdrp":"BRUSSELS","iata":"BRU","port":"1","city":"Sint-Pieters-Woluwe, Belgium"},{"bdrp":"SUSILO","iata":"SQG","city":"Sintang, Indonesia","port":"0"},{"bdrp":"SIOUX GATEWAY","iata":"SUX","port":"1","city":"Sioux City, Iowa, United States"},{"bdrp":"SIOUX FALLS","iata":"FSD","port":"1","city":"Sioux Falls, United States"},{"bdrp":"SKARDU A","iata":"KDU","port":"1","city":"Skardu, Pakistan, Pakistan"},{"bdrp":"PRISTINA","iata":"PRN","port":"1","city":"Slatina, Albania"},{"bdrp":"Adisumarmo","iata":"SOC","city":"Solo, Indonesia","port":"0"},{"bdrp":"TONGREN FENGHUANG","iata":"TEN","port":"1","city":"Songtao, Guizhou, China"},{"bdrp":"CHARLES M. SCHULZ u2013SONOMA COUNTY","iata":"STS","port":"1","city":"Sonoma County, California, United States"},{"bdrp":"Dominique Edward Osok","iata":"SOQ","city":"Sorong, Indonesia","port":"0"},{"bdrp":"SOUTHWEST FLORIDA","iata":"RSW","port":"1","city":"South Fort Myers, Florida, United States"},{"bdrp":"SOYO","iata":"SZA","port":"1","city":"Soyo, Angola, Angola"},{"bdrp":"SPOKANE","iata":"GEG","port":"1","city":"Spokane, United States"},{"bdrp":"SPRINGFIELD u2013BRANSON","iata":"SGF","port":"1","city":"Springfield, United States"},{"bdrp":"BANDARANAIKE","iata":"CMB","port":"1","city":"Sri Lanka, Sri Lanka"},{"bdrp":"PULKOVO","iata":"LED","port":"1","city":"St Petersburg, Russia"},{"bdrp":"HENRY E. ROHLSEN","iata":"STX","port":"1","city":"St. Croix, United States Virgin Islands, Virgin Islands, U.S."},{"bdrp":"L.F. WADE","iata":"BDA","port":"1","city":"St. David s Island, Bermuda"},{"bdrp":"UNIVERSITY PARK","iata":"SCE","port":"1","city":"State College, Pennsylvania, United States"},{"bdrp":"STUTTGART","iata":"STR","port":"1","city":"Stuttgart, Germany, Germany"},{"bdrp":"SULTAN ABDUL AZIZ SHAH","iata":"SZB","port":"1","city":"Subang, Malaysia"},{"bdrp":"FUKUSHIMA","iata":"FKS","port":"1","city":"Sukagawa, Japan"},{"bdrp":"SUKKUR","iata":"SKZ","port":"1","city":"Sukkur, Pakistan"},{"bdrp":"SULAIMANIYAH","iata":"ISU","port":"1","city":"Sulaimaniyah, Iraq"},{"bdrp":"SUMBAWA, BRANG BIJI","iata":"SWQ","city":"Sumbawa, Indonesia","port":"0"},{"bdrp":"SUNSHINE COAST","iata":"MCY","port":"1","city":"Sunshine Coast, Australia"},{"bdrp":"Juanda","iata":"SUB","city":"Surabaya, Indonesia","port":"0"},{"bdrp":"SURAT THANI","iata":"URT","port":"1","city":"Surat Thani, Thailand"},{"bdrp":"JOHAN ADOLF PENGEL","iata":"PBM","port":"1","city":"Suriname, Suriname"},{"bdrp":"LINKOPING CITY","iata":"LPI","port":"1","city":"Sweden, Sweden"},{"bdrp":"SYDNEY (KINGSFORD-SMITH)","iata":"SYD","port":"1","city":"Sydney, Australia"},{"bdrp":"TOWNSVILLE","iata":"TSV","port":"1","city":"TOWNSVILLE, Australia"},{"bdrp":"MARISCAL SUCRE","iata":"UIO","port":"1","city":"Tababela, Quito Canton, Ecuador"},{"bdrp":"WARUKIN","iata":"TJG","city":"Tabalong, Indonesia","port":"0"},{"bdrp":"TOUSSAINT L OUVERTURE","iata":"PAP","port":"1","city":"Tabarre, Haiti"},{"bdrp":"TABUBIL","iata":"TBG","port":"1","city":"Tabubil, Papua New Guinea"},{"bdrp":"TACHENG","iata":"TCG","port":"1","city":"Tacheng, Xinjiang, China"},{"bdrp":"Tacloban","iata":"TAC","port":"1","city":"Tacloban, Philippines"},{"bdrp":"Naha","iata":"NAH","city":"Tahuna, Indonesia","port":"0"},{"bdrp":"CHING CHUAN KANG AIR BASE","iata":"RMQ","port":"1","city":"Taichung, Taiwan"},{"bdrp":"JINGGANGSHAN","iata":"JGS","port":"1","city":"Taihe County, China"},{"bdrp":"TAINAN","iata":"TNN","port":"1","city":"Tainan, Taiwan"},{"bdrp":"TAIPEI SONGSHAN","iata":"TSA","port":"1","city":"Taipei, Taiwan"},{"bdrp":"TAIWAN TAOYUAN","iata":"TPE","port":"1","city":"Taipei, Taiwan"},{"bdrp":"TAIYUAN WUXU","iata":"TYN","port":"1","city":"Taiyuan, China"},{"bdrp":"TAKAMATSU","iata":"TAK","port":"1","city":"Takamatsu, Japan"},{"bdrp":"TALLAHASSEE","iata":"TLH","port":"1","city":"Tallahassee, Florida, United States"},{"bdrp":"TAMPOLAKA","iata":"TMC","city":"Tambolaka, Indonesia","port":"0"},{"bdrp":"TAMPA","iata":"TPA","port":"1","city":"Tampa, United States"},{"bdrp":"ANTONIO B. WON PAT","iata":"GUM","port":"1","city":"Tamuning, Guam"},{"bdrp":"TAMWORTH","iata":"TMW","port":"1","city":"Tamworth, Australia"},{"bdrp":"SOLA","iata":"SVG","port":"1","city":"Tananger, Norway"},{"bdrp":"TANJUNG MANIS","iata":"TGC","port":"1","city":"Tanjung Manis, Malaysia"},{"bdrp":"H.A.S HANANDJOEDDIN","iata":"TJQ","city":"Tanjung Pandan, Belitung, Indonesia","port":"0"},{"bdrp":"Raja Haji FIsabilillah","iata":"TNJ","city":"Tanjung Pinang, Indonesia","port":"0"},{"bdrp":"TANJUNG HARAPAN","iata":"TJS","city":"Tanjung Selor, Indonesia","port":"0"},{"bdrp":"AEK GODANG ","iata":"AEG","city":"Tapanuli Selatan-Aek Godang, Indonesia","port":"0"},{"bdrp":"JUWATA","iata":"TRK","city":"Tarakan, Indonesia","port":"0"},{"bdrp":"TARI","iata":"TIZ","port":"1","city":"Tari, Papua New Guinea"},{"bdrp":"TASHKENT","iata":"TAS","port":"1","city":"Tashkent, Uzbekistan, Uzbekistan"},{"bdrp":"LORD HOWE Island","iata":"LDH","port":"1","city":"Tasman Sea, Australia"},{"bdrp":"DEVONPORT","iata":"DPO","port":"1","city":"Tasmania, Australia"},{"bdrp":"TAWAU","iata":"TWU","port":"1","city":"Tawau, Malaysia"},{"bdrp":"TBILISI","iata":"TBS","port":"1","city":"Tbilisi, Georgia, Georgia"},{"bdrp":"TONCONTIN","iata":"TGU","port":"1","city":"Tegucigalpa, Honduras"},{"bdrp":"TEHRAN IMAM KHOMEINI","iata":"IKA","port":"1","city":"Tehran Imam Khomeini, Iran, Islamic Republic Of"},{"bdrp":"GRAN CANARIA","iata":"LPA","port":"1","city":"Telde, Spain"},{"bdrp":"ANSHAN TENGAO","iata":"AOG","port":"1","city":"Tengao Town, China"},{"bdrp":"NASHVILLE","iata":"BNA","port":"1","city":"Tennessee, United States"},{"bdrp":"KERTEH","iata":"KTE","port":"1","city":"Terengganu, Malaysia"},{"bdrp":"SULTAN BABULLAH","iata":"TTE","city":"Ternate, Indonesia","port":"0"},{"bdrp":"BARRANCO MINAS","iata":"NBB","port":"1","city":"Teusaquillo, Colombia"},{"bdrp":"THANH HOA","iata":"THD","port":"1","city":"Thanh Hoa, Vietnam"},{"bdrp":"BATTICALOA","iata":"BTC","port":"1","city":"Thimilathiu, Sri Lanka"},{"bdrp":"CALICUT","iata":"CCJ","port":"1","city":"Thiruvananthapuram, India"},{"bdrp":"THIVANDRUM","iata":"TRV","port":"1","city":"Thiruvananthapuram, India"},{"bdrp":"TIANJIN","iata":"TSN","port":"1","city":"Tianjin, China"},{"bdrp":"Mozes Kilangin","iata":"TIM","city":"Timika, Indonesia","port":"0"},{"bdrp":"TIRUCHILAPALLI","iata":"TRZ","port":"1","city":"Tiruchirapalli (Trichy), India"},{"bdrp":"TOAMASINA","iata":"TMM","port":"1","city":"Toamasina, Madagascar"},{"bdrp":"TOBELO","iata":"KAZ","city":"Tobelo, Indonesia","port":"0"},{"bdrp":"TOCUMEN","iata":"PTY","port":"1","city":"Tocumen, Panama, Panama"},{"bdrp":"TOKUSHIMA","iata":"TKS","port":"1","city":"Tokushima, Japan"},{"bdrp":"TOKYO, NARITA","iata":"NRT","port":"1","city":"Tokyo - Narita, Japan"},{"bdrp":"TOKYO, HANEDA","iata":"HND","port":"1","city":"Tokyo, Haneda, Japan"},{"bdrp":"TOLANARO","iata":"FTU","port":"1","city":"Tolanaro, Madagascar"},{"bdrp":"TOLI TOLI","iata":"TLI","city":"Toli-Toli, Indonesia","port":"0"},{"bdrp":"UNIVERSITY OF ILLINOIS WILLIARD","iata":"CMI","port":"1","city":"Tolono Township, United States"},{"bdrp":"FUAAMOTU","iata":"TBU","port":"1","city":"Tongatapu, Tonga"},{"bdrp":"TONGLIAO","iata":"TGO","port":"1","city":"Tongliao, Inner Mongolia, China"},{"bdrp":"NANTONG XINGDONG","iata":"NTG","port":"1","city":"Tongzhou, China"},{"bdrp":"FRANCISCO SARABIA","iata":"TRC","port":"1","city":"Torreon, Coahuila, Mexico"},{"bdrp":"TOTTORI","iata":"TTJ","port":"1","city":"Tottori, Japan"},{"bdrp":"TOYAMA","iata":"TOY","port":"1","city":"Toyama, Japan"},{"bdrp":"TRANG","iata":"TST","port":"1","city":"Trang, Thailand"},{"bdrp":"CHERRY CAPITAL","iata":"TVC","port":"1","city":"Traverse City, Michigan, United States"},{"bdrp":"TRIPOLI","iata":"TIP","port":"1","city":"Tripoli, Libyan Arab Jamahiriya"},{"bdrp":"TSUSHIMA","iata":"TSJ","port":"1","city":"Tsushima, Japan"},{"bdrp":"DUMATUBUN ","iata":"LUV","city":"Tual, Indonesia","port":"0"},{"bdrp":"TUCSON","iata":"TUS","port":"1","city":"Tucson, Arizona, United States"},{"bdrp":"TULSA","iata":"TUL","port":"1","city":"Tulsa, United States"},{"bdrp":"TUNIS u2013CARTHAGE","iata":"TUN","port":"1","city":"Tunis, Tunisia"},{"bdrp":"HUANGSHAN TUNXI","iata":"TXN","port":"1","city":"Tunxi, Huangshan City, China"},{"bdrp":"TURBAT","iata":"TUK","port":"1","city":"Turbat, Pakistan"},{"bdrp":"TUY HOA","iata":"TBB","port":"1","city":"Tuy Hoa, Vietnam"},{"bdrp":"GDANSK LECH WA u0142ESA","iata":"GDN","port":"1","city":"Tychy, Poland"},{"bdrp":"TYLER POUNDS","iata":"TYR","port":"1","city":"Tyler, Texas, United States"},{"bdrp":"YAMAGUCHI UBE","iata":"UBJ","port":"1","city":"Ube, Yamaguchi, Japan"},{"bdrp":"UBON RATCHATHANI","iata":"UBP","port":"1","city":"Ubon Ratchathani, Thailand"},{"bdrp":"UDONTHANI","iata":"UTH","port":"1","city":"Udon Thani, Thailand"},{"bdrp":"SULTAN HASANUDDIN","iata":"UPG","city":"Ujungpandang, Makassar, Indonesia","port":"0"},{"bdrp":"OSLO","iata":"OSL","port":"1","city":"Ullern, Norway"},{"bdrp":"ULURU","iata":"AYQ","port":"1","city":"Uluru, Australia"},{"bdrp":"BRISTOL","iata":"BRS","port":"1","city":"United Kingdom, United Kingdom"},{"bdrp":"BRUNSWICK GOLDEN ISLES","iata":"BQK","port":"1","city":"United States, Georgia"},{"bdrp":"APPLETON","iata":"ATW","port":"1","city":"United States, United States"},{"bdrp":"CHICAGO MIDWAY","iata":"MDW","port":"1","city":"United States, United States"},{"bdrp":"COLUMBUS METROPOLITAN","iata":"CSG","port":"1","city":"United States, United States"},{"bdrp":"DOTHAN","iata":"DHN","port":"1","city":"United States, United States"},{"bdrp":"SITKA ROCKY GUTIERREZ","iata":"SIT","port":"1","city":"United States, United States"},{"bdrp":"SOUTH BEND","iata":"SBN","port":"1","city":"United States, United States"},{"bdrp":"SOUTHWEST GEORGIA","iata":"ABY","port":"1","city":"United States, United States"},{"bdrp":"VALDOSTA","iata":"VLD","port":"1","city":"United States, United States"},{"bdrp":"VANIMO","iata":"VAI","port":"1","city":"Vanimo, Papua New Guinea"},{"bdrp":"HELSINKI-VANTAA","iata":"HEL","port":"1","city":"Vantaa, Finland"},{"bdrp":"BORYSPIL","iata":"KBP","port":"1","city":"Venice Island, Ukraine"},{"bdrp":"MARCO POLO","iata":"VCE","port":"1","city":"Venice, Italy"},{"bdrp":"BURLINGTON","iata":"BTV","port":"1","city":"Vermont, United States"},{"bdrp":"SEYCHELLES","iata":"SEZ","port":"1","city":"Victoria, Seychelles"},{"bdrp":"WATTAY","iata":"VTE","port":"1","city":"Vientiane, Laos"},{"bdrp":"ANTONIO RIVERA RODRIGUEZ","iata":"VQS","port":"1","city":"Vieques, Puerto Rico"},{"bdrp":"HEWANORRA","iata":"UVF","port":"1","city":"Vieux Fort, Saint Lucia"},{"bdrp":"VIGO u2013PEINADOR","iata":"VGO","port":"1","city":"Vigo, Spain"},{"bdrp":"PORTO SANTO","iata":"PXO","port":"1","city":"Vila Do Porto, Portugal"},{"bdrp":"VALLADOLID","iata":"VLL","port":"1","city":"Villanubla, Spain"},{"bdrp":"VINH","iata":"VII","port":"1","city":"Vinh, Vietnam"},{"bdrp":"VISAKHAPATNAM","iata":"VTZ","port":"1","city":"Visakhapatnam, India"},{"bdrp":"SOFIA","iata":"SOF","port":"1","city":"Vitoshka Boulevard, Bulgaria"},{"bdrp":"WELLINGTON","iata":"WLG","port":"1","city":"WELLINGTON, New Zealand"},{"bdrp":"WACO","iata":"ACT","port":"1","city":"Waco, United States"},{"bdrp":"WAINGAPU","iata":"WGP","city":"Waingapu, Indonesia","port":"0"},{"bdrp":"NOTO SATOYAMA","iata":"NTQ","port":"1","city":"Wajima, Japan"},{"bdrp":"MATAHORA","iata":"WNI","city":"Wakatobi, Indonesia","port":"0"},{"bdrp":"WAKKANAI","iata":"WKJ","port":"1","city":"Wakkanai, Japan"},{"bdrp":"CARDIFF","iata":"CWL","port":"1","city":"Wales, Wallis And Futuna"},{"bdrp":"HIHIFO","iata":"WLS","port":"1","city":"Wallis Island, Wallis And Futuna"},{"bdrp":"WANGI WANGI, MATAHORA","iata":"WGI","city":"Wangi wangi, Indonesia","port":"0"},{"bdrp":"WANZHOU WUQIAO","iata":"WXN","port":"1","city":"Wanzhou, China"},{"bdrp":"WAPENAMANDA","iata":"WBM","port":"1","city":"Wapenamanda, Papua New Guinea"},{"bdrp":"WATERLOO","iata":"ALO","port":"1","city":"Waterloo, United States"},{"bdrp":"WARSAWA FREDERIC CHOPIN","iata":"WAW","port":"1","city":"Wawrzyszew, Poland"},{"bdrp":"WEIPA","iata":"WEI","port":"1","city":"Weipa, Australia"},{"bdrp":"WENZHOU LONGWAN","iata":"WNZ","port":"1","city":"Wenzhou, China"},{"bdrp":"WEWAK","iata":"WWK","port":"1","city":"Wewak, Papua New Guinea"},{"bdrp":"WESTCHESTER COUNTY","iata":"HPN","port":"1","city":"White Plains, United States"},{"bdrp":"WICHITA FALLS MUNICIPAL","iata":"SPS","port":"1","city":"Wichita Falls, Texas, United States"},{"bdrp":"WICHITA DWIGHT D. EISENHOWER","iata":"ICT","port":"1","city":"Wichita, United States"},{"bdrp":"HATO","iata":"CUR","port":"1","city":"Willemstad, Venezuela"},{"bdrp":"WILLIAMSPORT","iata":"IPT","port":"1","city":"Williamsport, United States"},{"bdrp":"HOSEA KUTAKO","iata":"WDH","port":"1","city":"Windhoek, Namibia"},{"bdrp":"ALBURY","iata":"ABX","port":"1","city":"Wodonga, Australia"},{"bdrp":"WONJU","iata":"WJU","port":"1","city":"Wonju, South Korea"},{"bdrp":"REGION OF WATERLOO","iata":"YKF","port":"1","city":"Woolwich, Canada"},{"bdrp":"NEWCASTLE","iata":"NCL","port":"1","city":"Workington, United Kingdom"},{"bdrp":"WILMINGTON","iata":"ILM","port":"1","city":"Wrightsboro, United States"},{"bdrp":"WUHAN TIANHE","iata":"WUH","port":"1","city":"Wuhan, China"},{"bdrp":"WUYISHAN","iata":"WUS","port":"1","city":"Wuyishan City, China"},{"bdrp":"XI AN XIANYANG","iata":"XIY","port":"1","city":"Xi an, China"},{"bdrp":"XIANGYANG LIUJI","iata":"XFN","port":"1","city":"Xiangyang, China"},{"bdrp":"ZHANJIANG","iata":"ZHA","port":"1","city":"Xiashan District, Zhanjiang, China"},{"bdrp":"XILINHOT","iata":"XIL","port":"1","city":"Xilinhot, China"},{"bdrp":"SHIJIAZHUANG ZHENGDING","iata":"SJW","port":"1","city":"Xinchengpu Town, China"},{"bdrp":"XINGYI WANFENGLIN","iata":"ACX","port":"1","city":"Xingyi, China"},{"bdrp":"NALATI","iata":"NLT","port":"1","city":"Xinyuan County, China"},{"bdrp":"ZUNYI XINZHOU","iata":"ZYI","port":"1","city":"Xinzhou, China"},{"bdrp":"YUMA","iata":"YUM","port":"1","city":"YUMA, United States"},{"bdrp":"YANAN ERSHILIPU","iata":"ENY","port":"1","city":"Yanan, China"},{"bdrp":"YANGOON","iata":"RGN","port":"1","city":"Yangoon, Myanmar"},{"bdrp":"WENSHAN PUZHEHEI","iata":"WNH","port":"1","city":"Yanshan County, China"},{"bdrp":"YANTAI PENGLAI","iata":"YNT","port":"1","city":"Yantai, Shandong, China"},{"bdrp":"JINAN YAOQIANG","iata":"TNA","port":"1","city":"Yaoqiang, Licheng District, China"},{"bdrp":"YAOUNDE NSIMALEN","iata":"NSI","port":"1","city":"Yaounde, Cameroon"},{"bdrp":"LEEDS BRADFORD","iata":"LBA","port":"1","city":"Yeadon, United Kingdom"},{"bdrp":"YEOSU","iata":"RSU","port":"1","city":"Yeosu, South Jeolla Province, South Korea, South Korea"},{"bdrp":"YICHANG SANXIA","iata":"YIH","port":"1","city":"Yichang, China"},{"bdrp":"YICHUN LINDU","iata":"LDS","port":"1","city":"Yichun, China"},{"bdrp":"URUMQI DIWOPU","iata":"URC","port":"1","city":"Yili Hasakezizhizhou, China"},{"bdrp":"YINING","iata":"YIN","port":"1","city":"Yining, Xinjiang, China"},{"bdrp":"YIWU","iata":"YIW","port":"1","city":"Yiwu, China"},{"bdrp":"Adi Sutjipto","iata":"JOG","city":"Yogyakarta, Indonesia","port":"0"},{"bdrp":"MIHO u2013YONAGO","iata":"YGJ","port":"1","city":"Yonago, Japan"},{"bdrp":"YUNCHENG GUANGONG","iata":"YCU","port":"1","city":"Yuncheng, China"},{"bdrp":"YUZHNO-SAKHALINSK","iata":"UUS","port":"1","city":"Yuzhno-Sakhalinsk, Russia, Russia"},{"bdrp":"ZAGREB","iata":"ZAG","port":"1","city":"Zagreb, Croatia"},{"bdrp":"ABEID AMANI KARUME","iata":"ZNZ","port":"1","city":"Zanzibar Town, Tanzania"},{"bdrp":"ZARAGOZA","iata":"ZAZ","port":"1","city":"Zaragoza, Spain"},{"bdrp":"LJUBLJANA JOZE PUCNIK","iata":"LJU","port":"1","city":"Zgornji Brnik, Slovenia"},{"bdrp":"ZHANGJIAJIE","iata":"DYG","port":"1","city":"Zhangjiajie, China"},{"bdrp":"ZHAOTONG","iata":"ZAT","port":"1","city":"Zhaotong, China"},{"bdrp":"ZHOB","iata":"PZH","port":"1","city":"Zhob, Pakistan"},{"bdrp":"ZHOUSHAN PUTUOSHAN","iata":"HSN","port":"1","city":"Zhoushan, China"},{"bdrp":"IXTAPA-ZIHUATANEJO","iata":"ZIH","port":"1","city":"Zihuatanejo, Guerrero, Mexico"},{"bdrp":"ZURICH","iata":"ZRH","port":"1","city":"Zurich, Switzerland"}]}